{"type": "FeatureCollection", "features": [{"type": "Feature", "properties": {"url": null, "title": "Fahrradfreundlichste Kreuzung Berlins mit Flexipoller sch\u00fctzen\n", "bezirk": "Friedrichshain-Kreuzberg", "typ": null, "date": null, "dsnr": "DS-1322-IV", "ausschuss": "Umwelt", "address": ["Moritzplatz", ""], "text": "\n\n\n\n\nDie Bezirksverordnetenversammlung m\u00f6ge beschlie\u00dfen:\u00a0Das Bezirksamt wird beauftragt, zu pr\u00fcfen, wie der Radverkehr an Berlins fahrradfreundlichster Kreuzung, dem Moritzplatz, besser vor PKW und LKW gesch\u00fctzt werden kann. Dabei soll der Kreisverkehr mit Vorfahrt f\u00fcr den Radverkehr unbedingt erhalten bleiben.\u00a0 \u00a0Der Bezirksverordnetenversammlung ist bis Februar 2015 zu berichten.\u00a0Begr\u00fcndung:\u00a0Der Moritzplatz ist Berlins fahrradfreundlichste Kreuzung, weil der Radverkehr - bedingt durch den Kreisverkehr - immer Vorfahrt hat. Gleichzeitig ist der Moritzplatz eine der Kreuzungen Berlins mit den meisten Unf\u00e4llen, bei denen zudem oft Fahrradfahrer*innen betroffen sind. Gef\u00e4hrliche Situationen entstehen insbesondere dann, wenn Autos und LKW zu Unrecht die Spur des Radverkehrs kreuzen. Die Situation k\u00f6nnte behoben werden, indem die Spur durch Flexipoller besser sichtbar wird und der Radstreifen und seiner Benutzer*innen dadurch besser\u00a0 besch\u00fctzt werden. Der FahrRat, das Beratungsgremium des Bezirksamtes f\u00fcr den Radverkehr, hat sich bereits f\u00fcr den Einsatz von Flexipollern am Moritzplatz ausgesprochen. \u00a0\u00a0BVV 24.09.2014Die Bezirksverordnetenversammlung beschlie\u00dft:\u00a0\u00dcberweisung: Ausschuss f\u00fcr Umwelt, Klimaschutz, Verkehr und Immobilien \u00a0\u00a0UVKI 12.11.2014Die Bezirksverordnetenversammlung m\u00f6ge beschlie\u00dfen:\u00a0Das Bezirksamt wird beauftragt, zu pr\u00fcfen, wie der Radverkehr an Berlins fahrradfreundlichster Kreuzung, dem Moritzplatz, besser vor PKW und LKW gesch\u00fctzt werden kann. Dabei soll der Kreisverkehr mit Vorfahrt f\u00fcr den Radverkehr unbedingt erhalten bleiben.\u00a0 \u00a0Der Bezirksverordnetenversammlung ist bis Februar 2015 zu berichten.\u00a0\u00a0BVV 26.11.2014Die Bezirksverordnetenversammlung beschlie\u00dft:\u00a0Das Bezirksamt wird beauftragt, zu pr\u00fcfen, wie der Radverkehr an Berlins fahrradfreundlichster Kreuzung, dem Moritzplatz, besser vor PKW und LKW gesch\u00fctzt werden kann. Dabei soll der Kreisverkehr mit Vorfahrt f\u00fcr den Radverkehr unbedingt erhalten bleiben.\u00a0 \u00a0Der Bezirksverordnetenversammlung ist bis Februar 2015 zu berichten.\u00a0\u00a0Die Bezirksverordnetenversammlung m\u00f6ge beschlie\u00dfen:\u00a0Die Vorlage wird zur Kenntnis genommen. \u00a0\u00a0BVV 23.09.2015Die Bezirksverordnetenversammlung beschlie\u00dft:\u00a0\u00dcberweisung: Ausschuss f\u00fcr Umwelt, Klimaschutz, Verkehr und Immobilien \u00a0\u00a0UVKI 14.10.2015Die Bezirksverordnetenversammlung m\u00f6ge beschlie\u00dfen:\u00a0Die Vorlage wird zur Kenntnis genommen. \u00a0\u00a0BVV 28.10.2015Die Bezirksverordnetenversammlung beschlie\u00dft:\u00a0Die Vorlage wird zur Kenntnis genommen. \u00a0\u00a0\n\n\n/*<![CDATA[*/\nif (typeof DartIvwKategorie !== \"string\") window.DartIvwKategorie = \"boUndefined\";\n\nvar CP = \"//boss.berlinonline.de/cp.php?a=berlin&amp;r=\"+escape(document.referrer)+\"&amp;cat=\"+DartIvwKategorie+\"&amp;p=\"+escape(document.location)+\"&amp;d=\"+(Math.random()*100000);\ndocument.write(\"<img src=\\\"\"+CP+\"\\\" width=\\\"1\\\" height=\\\"1\\\" alt=\\\"\\\" id=\\\"cp_pixel\\\" style=\\\"position:absolute;width:1px;height:1px;\\\"/>\");\n/*]]>*/\n\n\n\n\nvar _paq = _paq || [];\n_paq.push([\"setDocumentTitle\", document.domain + \"/\" + document.title]);\n_paq.push([\"setCustomVariable\",1,\"Dart.active\",(typeof DartActive == \"boolean\" ? \"y\" : \"n\"),\"page\"]);\n_paq.push([\"trackPageView\"]);\n_paq.push([\"enableLinkTracking\"]);\n(function() {\nvar u=((\"https:\" == document.location.protocol) ? \"https\" : \"http\") + \"://piwik.berlinonline.de/\";\n_paq.push([\"setTrackerUrl\", u+\"piwik.php\"]);\n_paq.push([\"setSiteId\", \"1\"]);\nvar d=document, g=d.createElement(\"script\"), s=d.getElementsByTagName(\"script\")[0]; g.type=\"text/javascript\";\ng.defer=true; g.async=true; g.src=u+\"piwik.js\"; s.parentNode.insertBefore(g,s);\n})();\n\n\n\n\n\n\n\n\nvar iam_data = {\n\"mg\":\"yes\",\n\"cp\":DartIvwKategorie,\n\"st\":\"berlin\",\n\"sv\":(location.pathname==\"/\"?\"ke\":\"in\"),\n\"co\":location.hostname\n}\niom.c(iam_data,1);\n\n\n\n\n"}, "geometry": {"type": "Point", "coordinates": [13.4103815, 52.5035393]}}]}