{"type": "FeatureCollection", "features": [{"geometry": {"type": "Point", "coordinates": [13.226944, 52.561944]}, "type": "Feature", "properties": {"ausschuss": "", "bezirk": "Friedrichshain-Kreuzberg", "address": "", "title": "Baerwaldbad retten!\n", "url": null, "date": null, "typ": null, "text": "\n\n\n\n\nDie Bezirksverordnetenversammlung m\u00f6ge beschlie\u00dfen:\u00a0Das BA wird aufgefordert, den Erbbaurechtsnehmer des Baerwaldbades darin zu unterst\u00fctzen, schnellstm\u00f6glich einen Ma\u00dfnahmenkatalog zur Beseitigung der hygienischen und baulichen M\u00e4ngel des Bades vorzulegen, um die dort stattfindenden Angebote f\u00fcr den Schulsportunterricht bzw. den Schwimmsport insgesamt zu sichern. \u00a0Der BVV ist bis September 2015 zu berichten.\u00a0Begr\u00fcndung:\u00a0Die hygienischen Zust\u00e4nde im Baerwaldbad sind gesundheitsgef\u00e4hrdend, wie das Gesundheitsamt des Bezirks pr\u00e4zise belegt hat. Es existiert aktuell keine detaillierte Kenntnis aller M\u00e4ngel und der kausalen Zusammenh\u00e4nge zwischen Ursachen und Wirkungen, weshalb ein qualifizierter Ma\u00dfnahmenplan dringend erarbeitet werden muss.\u00a0\u00a0BVV 18.06.2015Die Bezirksverordnetenversammlung beschlie\u00dft:\u00a0Der Antrag wird abgelehnt.\n\n\n/*<![CDATA[*/\nif (typeof DartIvwKategorie !== \"string\") window.DartIvwKategorie = \"boUndefined\";\n\nvar CP = \"//boss.berlinonline.de/cp.php?a=berlin&amp;r=\"+escape(document.referrer)+\"&amp;cat=\"+DartIvwKategorie+\"&amp;p=\"+escape(document.location)+\"&amp;d=\"+(Math.random()*100000);\ndocument.write(\"<img src=\\\"\"+CP+\"\\\" width=\\\"1\\\" height=\\\"1\\\" alt=\\\"\\\" id=\\\"cp_pixel\\\" style=\\\"position:absolute;width:1px;height:1px;\\\"/>\");\n/*]]>*/\n\n\n\n\nvar _paq = _paq || [];\n_paq.push([\"setDocumentTitle\", document.domain + \"/\" + document.title]);\n_paq.push([\"setCustomVariable\",1,\"Dart.active\",(typeof DartActive == \"boolean\" ? \"y\" : \"n\"),\"page\"]);\n_paq.push([\"trackPageView\"]);\n_paq.push([\"enableLinkTracking\"]);\n(function() {\nvar u=((\"https:\" == document.location.protocol) ? \"https\" : \"http\") + \"://piwik.berlinonline.de/\";\n_paq.push([\"setTrackerUrl\", u+\"piwik.php\"]);\n_paq.push([\"setSiteId\", \"1\"]);\nvar d=document, g=d.createElement(\"script\"), s=d.getElementsByTagName(\"script\")[0]; g.type=\"text/javascript\";\ng.defer=true; g.async=true; g.src=u+\"piwik.js\"; s.parentNode.insertBefore(g,s);\n})();\n\n\n\n\n\n\n\n\nvar iam_data = {\n\"mg\":\"yes\",\n\"cp\":DartIvwKategorie,\n\"st\":\"berlin\",\n\"sv\":(location.pathname==\"/\"?\"ke\":\"in\"),\n\"co\":location.hostname\n}\niom.c(iam_data,1);\n\n\n\n\n", "dsnr": "DS-1740-IV"}}]}