{"type": "FeatureCollection", "features": [{"geometry": {"type": "Point", "coordinates": [13.4240721, 52.5245048]}, "type": "Feature", "properties": {"ausschuss": "Umwelt", "bezirk": "Friedrichshain-Kreuzberg", "address": ["Mollstra\u00dfe", ""], "title": "Einbahnstra\u00dfe am Platz der Vereinten Nationen \u00f6ffnen\n", "url": null, "date": null, "typ": null, "text": "\n\n\n\n\nDie Bezirksverordnetenversammlung m\u00f6ge beschlie\u00dfen:\u00a0Das Bezirksamt wird beauftragt, zu pr\u00fcfen, ob die Einbahnstra\u00dfe am Platz der Vereinten Nationen 15-22/ Lichtenberger Stra\u00dfe 1 zwischen Mollstra\u00dfe und Weydemeyerstra\u00dfe f\u00fcr den gegengerichteten Radverkehr ge\u00f6ffnet werden kann. \u00a0Begr\u00fcndung: \u00a0In der Radverkehrsstrategie des Berliner Senats wird ausdr\u00fccklich empfohlen, weitere Einbahnstra\u00dfen f\u00fcr den Radverkehr zu \u00f6ffnen. Dazu soll systematisch \u00fcberpr\u00fcft werden, \"welche Einbahnstra\u00dfen f\u00fcr den Radverkehr in Gegenrichtung noch ge\u00f6ffnet werden k\u00f6nnen, um Umwege zu vermeiden.\" (http://www.stadtentwicklung.berlin.de/verkehr/politik_planung/rad/strategie/de/m_strassen.shtml)\u00a0Ein ausgezeichneter Kandidat f\u00fcr eine solche \u00d6ffnung ist die Einbahnstra\u00dfe an Platz der Vereinten Nationen 15-22/ Lichtenberger Stra\u00dfe 1 zwischen Mollstra\u00dfe und Weydemeyerstra\u00dfe. Auf Google-Maps: https://www.google.de/maps/place/Lichtenberger+Stra%C3%9Fe+1/@52.5226835,13.426375,16z/data=!4m2!3m1!1s0x47a84e16f29e8621:0x55acfd37a23a64c9Es handelt sich um einer reine Wohnstra\u00dfe mit Anwohnerparkpl\u00e4tzen ineiner 30er Zone ohne nennenswerten KFZ-Verkehr.\u00a0F\u00fcr den Radverkehr beschleunigt\u00a0 dieses Teilst\u00fcck eine attraktive Querverbindung Richtung Bersarinplatz/Frankfurter Tor via Palisadenstra\u00dfe/Weidenweg. Diese Verbindungszug wird schon jetzt von relativ vielen RadfahrerInnen verbotswidrig genutzt - bisher illegal. Dieses Verbot f\u00fcr Fahrradfahrerinnen und Fahrradfahrer ist nicht sinnvoll.\u00a0 \u00a0BVV 27.08.2014Die Bezirksverordnetenversammlung beschlie\u00dft:\u00a0\u00dcberweisung: Ausschuss f\u00fcr Umwelt, Klimaschutz, Verkehr und Immobilien \u00a0\u00a0UVKI 10.09.2014Die Bezirksverordnetenversammlung m\u00f6ge beschlie\u00dfen:\u00a0Das Bezirksamt wird beauftragt, zu pr\u00fcfen, ob die Einbahnstra\u00dfe am Platz der Vereinten Nationen 15-22/ Lichtenberger Stra\u00dfe 1 zwischen Mollstra\u00dfe und Weydemeyerstra\u00dfe f\u00fcr den gegengerichteten Radverkehr ge\u00f6ffnet werden kann. \u00a0\u00a0BVV 24.09.2014Die Bezirksverordnetenversammlung beschlie\u00dft:\u00a0Das Bezirksamt wird beauftragt, zu pr\u00fcfen, ob die Einbahnstra\u00dfe am Platz der Vereinten Nationen 15-22/ Lichtenberger Stra\u00dfe 1 zwischen Mollstra\u00dfe und Weydemeyerstra\u00dfe f\u00fcr den gegengerichteten Radverkehr ge\u00f6ffnet werden kann. \u00a0\u00a0Die Bezirksverordnetenversammlung m\u00f6ge beschlie\u00dfen:\u00a0Die Vorlage wird zur Kenntnis genommen. \u00a0\u00a0BVV 24.06.2015Die Bezirksverordnetenversammlung beschlie\u00dft:\u00a0\u00dcberweisung: Ausschuss f\u00fcr Umwelt, Klimaschutz, Verkehr und Immobilien \u00a0\u00a0UVKI 14.10.2015Die Bezirksverordnetenversammlung m\u00f6ge beschlie\u00dfen:\u00a0Die Vorlage wird zur Kenntnis genommen. \u00a0\u00a0BVV 28.10.2015Die Bezirksverordnetenversammlung beschlie\u00dft:\u00a0Die Vorlage wird zur Kenntnis genommen. \u00a0\u00a0\n\n\n/*<![CDATA[*/\nif (typeof DartIvwKategorie !== \"string\") window.DartIvwKategorie = \"boUndefined\";\n\nvar CP = \"//boss.berlinonline.de/cp.php?a=berlin&amp;r=\"+escape(document.referrer)+\"&amp;cat=\"+DartIvwKategorie+\"&amp;p=\"+escape(document.location)+\"&amp;d=\"+(Math.random()*100000);\ndocument.write(\"<img src=\\\"\"+CP+\"\\\" width=\\\"1\\\" height=\\\"1\\\" alt=\\\"\\\" id=\\\"cp_pixel\\\" style=\\\"position:absolute;width:1px;height:1px;\\\"/>\");\n/*]]>*/\n\n\n\n\nvar _paq = _paq || [];\n_paq.push([\"setDocumentTitle\", document.domain + \"/\" + document.title]);\n_paq.push([\"setCustomVariable\",1,\"Dart.active\",(typeof DartActive == \"boolean\" ? \"y\" : \"n\"),\"page\"]);\n_paq.push([\"trackPageView\"]);\n_paq.push([\"enableLinkTracking\"]);\n(function() {\nvar u=((\"https:\" == document.location.protocol) ? \"https\" : \"http\") + \"://piwik.berlinonline.de/\";\n_paq.push([\"setTrackerUrl\", u+\"piwik.php\"]);\n_paq.push([\"setSiteId\", \"1\"]);\nvar d=document, g=d.createElement(\"script\"), s=d.getElementsByTagName(\"script\")[0]; g.type=\"text/javascript\";\ng.defer=true; g.async=true; g.src=u+\"piwik.js\"; s.parentNode.insertBefore(g,s);\n})();\n\n\n\n\n\n\n\n\nvar iam_data = {\n\"mg\":\"yes\",\n\"cp\":DartIvwKategorie,\n\"st\":\"berlin\",\n\"sv\":(location.pathname==\"/\"?\"ke\":\"in\"),\n\"co\":location.hostname\n}\niom.c(iam_data,1);\n\n\n\n\n", "dsnr": "DS-1245-IV"}}]}