{"type": "FeatureCollection", "features": [{"geometry": {"type": "Point", "coordinates": [13.4103815, 52.5035393]}, "type": "Feature", "properties": {"ausschuss": "Kultur", "bezirk": "Friedrichshain-Kreuzberg", "address": ["Moritzplatz", ""], "title": "Soziokulturelle Angebote in der Otto-Suhr-Siedlung und im Sozialraum Moritzplatz  \n", "url": null, "date": null, "typ": null, "text": "\n\n\n\n\nDie Bezirksverordnetenversammlung m\u00f6ge beschlie\u00dfen:\u00a0Das Bezirksamt wird beauftragt zu pr\u00fcfen, welche soziokulturellen Angebote f\u00fcr die Bewohner*innen des Sozialraums Moritzplatz/Otto-Suhr-Siedlung entwickelt werden k\u00f6nnen, die geeignet w\u00e4ren, die durch die Verlagerung der Bona-Peiser-Bibliothek entstandene L\u00fccke zumindest in Bezug auf die Funktion der Bibliothek als eines nichtkommerziellen kulturellen Treffpunktes und Kommunikationsortes f\u00fcr den Kiez zu schlie\u00dfen.\u00a0Hierzu ist Kontakt mit den bereits im Sozialraum involvierten Akteur*innen, Initiativen und Tr\u00e4gern\u00a0 - unter besonderer Ber\u00fccksichtigung der Initiative zur Rettung der Bona-Peiser-Bibliothek -aufzunehmen und ein runder Tisch zur gemeinsamen Ideenentwicklung zu initiieren. Die Anwohner und Anwohnerinnen sind in diesen Prozess mit einzubeziehen.\u00a0Begr\u00fcndung: \u00a0Der Bezirk sieht sich durch den durch das Land beschlossenen Personalabbau in den Bezirken nicht mehr in der Lage, die Bona-Peiser_Bibliothek in der Oranienstr. als Bibliotheksstandort weiter zu f\u00fchren, da die personelle Besetzung der bezirklichen Bibliotheken schon bereits jetzt kaum ausreicht, das bisherige Angebot auch qualitativ aufrecht zu erhalten. Zumindest die Versorgung der Anwohner*innen bez\u00fcglich der spezifischen Bibliotheksangebote wird auch weiterhin\u00a0 durch die nahe gelegene Mittelpunktsbibliothek in der Adalbertstr. gew\u00e4hrleistet. Aber f\u00fcr die Bewohner rund um die Otto-Suhr-Siedlung mit all ihren Problemen ist die Bona-Peiser-Bibliothek weitaus mehr als nur ein Ort zum Lesen und Ausleihen von B\u00fcchern. \"Er ist auch ein Treffpunkt, gerade f\u00fcr Leute, die sich aus finanziellen Gr\u00fcnden viele andere Angebote nicht leisten k\u00f6nnen.\" \u00a0BVV 27.08.2014Die Bezirksverordnetenversammlung beschlie\u00dft:\u00a0\u00dcberweisung: Ausschuss f\u00fcr Kultur und Bildung \u00a0\u00a0KuBi 02.09.2014Die Drucksache wird zur\u00fcckgezogen.\u00a0\n\n\n/*<![CDATA[*/\nif (typeof DartIvwKategorie !== \"string\") window.DartIvwKategorie = \"boUndefined\";\n\nvar CP = \"//boss.berlinonline.de/cp.php?a=berlin&amp;r=\"+escape(document.referrer)+\"&amp;cat=\"+DartIvwKategorie+\"&amp;p=\"+escape(document.location)+\"&amp;d=\"+(Math.random()*100000);\ndocument.write(\"<img src=\\\"\"+CP+\"\\\" width=\\\"1\\\" height=\\\"1\\\" alt=\\\"\\\" id=\\\"cp_pixel\\\" style=\\\"position:absolute;width:1px;height:1px;\\\"/>\");\n/*]]>*/\n\n\n\n\nvar _paq = _paq || [];\n_paq.push([\"setDocumentTitle\", document.domain + \"/\" + document.title]);\n_paq.push([\"setCustomVariable\",1,\"Dart.active\",(typeof DartActive == \"boolean\" ? \"y\" : \"n\"),\"page\"]);\n_paq.push([\"trackPageView\"]);\n_paq.push([\"enableLinkTracking\"]);\n(function() {\nvar u=((\"https:\" == document.location.protocol) ? \"https\" : \"http\") + \"://piwik.berlinonline.de/\";\n_paq.push([\"setTrackerUrl\", u+\"piwik.php\"]);\n_paq.push([\"setSiteId\", \"1\"]);\nvar d=document, g=d.createElement(\"script\"), s=d.getElementsByTagName(\"script\")[0]; g.type=\"text/javascript\";\ng.defer=true; g.async=true; g.src=u+\"piwik.js\"; s.parentNode.insertBefore(g,s);\n})();\n\n\n\n\n\n\n\n\nvar iam_data = {\n\"mg\":\"yes\",\n\"cp\":DartIvwKategorie,\n\"st\":\"berlin\",\n\"sv\":(location.pathname==\"/\"?\"ke\":\"in\"),\n\"co\":location.hostname\n}\niom.c(iam_data,1);\n\n\n\n\n", "dsnr": "DS-1241-IV"}}]}