{"type": "FeatureCollection", "features": [{"type": "Feature", "properties": {"url": null, "title": "Vergabe der Sportst\u00e4tten Fredersdorferstra\u00dfe\n", "bezirk": "Friedrichshain-Kreuzberg", "typ": null, "date": null, "dsnr": "DS-2054-II", "ausschuss": "", "address": ["Fredersdorferstra\u00dfe", ""], "text": "\n\n\n\n\n\n\nIch\nfrage das Bezirksamt:\n\u00a0\n\u00a0\n\nWurden bei der Vergabe der\n     Sportst\u00e4tte Fredersdorferstra\u00dfe M\u00e4dchen \u2013 und Frauensportvereine\n     ber\u00fccksichtigt?\nWenn ja, um welche Sportgruppen\n     handelt es sich?\nWenn nein, gab es keine\n     Nachfrage von Frauen- und M\u00e4dchensportgruppen?\n\n\u00a0\nFrau\nKlebba:\nZu 1:\nSeit dem 5.2.06 erfolgt die Nutzung der Sporthalle nach Sanierung auf der\nGrundlage \u00fcberarbeiteter Vergabepl\u00e4ne, die auch eine l\u00e4ngere Schulnutzung\nvorsehen und zwar Montags bis Mittwochs bis 18.00 ist dort Schulnutzung\nvorgesehen und Donnerstag bis 17,00 und Freitags bis 16.30 aber bei der Vergabe\nvon Nutzungszeiten wurden selbstverst\u00e4ndlich auch M\u00e4dchen- und\nFrauensportvereine ber\u00fccksichtigt. Zur Frage 2: Es werden ber\u00fccksichtigt SV\nWeberwiese mit Frauengymnastik, Empor Brandenburger Tor mit Frauengymnastik und\nFSC Friedrichshain mit Gymnastik, Tanz, Chearleading \u2013 insgesamt auf 35\nTeilnehmerinnen\u00a0 anwachsen. Seit M\u00e4rz\n2006 wurde der Polizeisportverein mit der Damenfaustballsektion ber\u00fccksichtigt.\nDie Sportvereine Medizin Friedrichshain mit Volleyball, Motor Ost mit\nVolleyball und FSG Weberwiese sind mit Gymnastik und Volleyball in gemischten\nSportgruppen dort ans\u00e4ssig. ZU 3: Es gibt also eine Nachfrage nach M\u00e4dchen- und\nFrauensport allerdings muss man sagen, die Nachfrage zur Belegung der\nVergabezeiten erfolgte relativ z\u00f6gerlich und auch jetzt gibt es noch eine\nNutzungszeit am Freitag von 18.00 bis 20.00, die noch an interessierte\nFrauensportgruppen vergeben werden kann. Bisher war die Nachfrage in diesen\nZeitsegment f\u00fcr Frauensportgruppen eher gering.\n\u00a0\n\u00a0Frau Schmidt-Stanojevic:\nSind\nihnen Gr\u00fcnde daf\u00fcr bekannt, warum die Nachfrage von frauen- und\nM\u00e4dchensportgruppen z\u00f6gerlich verl\u00e4uft.\n\u00a0\nFrau\nKlebba:\nWir haben\nja insgesamt das Projekt der M\u00e4dchen- und Frauensportf\u00f6rderung um sozusagen\ndort motivierend und etablierend t\u00e4tig werden zu k\u00f6nnen und insofern ist es\nunsere gemeinsame Aufgabe dort auch die Vergabe oder die Vergabe enstpr.\nauszurichten. Da haben wir ja unsere vielf\u00e4ltigsten Formen zur Unterst\u00fctzung\ndieses Vorhabens und diese Zeiten von 18.00 bis 20.00, das sind auch\nfamiliengenutzte Zwischenzeiten. Das sind Zeiten, wo man sagen kann, da ist zu\nHause der Abendbrottisch, die Kinder m\u00fcssen f\u00fcrs Bett fertig gemacht werden,\nalso Familienzeit und insofern kann man sagen, m\u00f6glicherweise ist das ein\nGrund. Ich will nicht sagen,\u00a0 das ist der\nausschlie\u00dfliche Grund, dem m\u00fcssen wir nach gehen, dass die Zeiten eher weniger\nnachgefragt werden. \n\n\n\n\n/*<![CDATA[*/\nif (typeof DartIvwKategorie !== \"string\") window.DartIvwKategorie = \"boUndefined\";\n\nvar CP = \"//boss.berlinonline.de/cp.php?a=berlin&amp;r=\"+escape(document.referrer)+\"&amp;cat=\"+DartIvwKategorie+\"&amp;p=\"+escape(document.location)+\"&amp;d=\"+(Math.random()*100000);\ndocument.write(\"<img src=\\\"\"+CP+\"\\\" width=\\\"1\\\" height=\\\"1\\\" alt=\\\"\\\" id=\\\"cp_pixel\\\" style=\\\"position:absolute;width:1px;height:1px;\\\"/>\");\n/*]]>*/\n\n\n\n\nvar _paq = _paq || [];\n_paq.push([\"setDocumentTitle\", document.domain + \"/\" + document.title]);\n_paq.push([\"setCustomVariable\",1,\"Dart.active\",(typeof DartActive == \"boolean\" ? \"y\" : \"n\"),\"page\"]);\n_paq.push([\"trackPageView\"]);\n_paq.push([\"enableLinkTracking\"]);\n(function() {\nvar u=((\"https:\" == document.location.protocol) ? \"https\" : \"http\") + \"://piwik.berlinonline.de/\";\n_paq.push([\"setTrackerUrl\", u+\"piwik.php\"]);\n_paq.push([\"setSiteId\", \"1\"]);\nvar d=document, g=d.createElement(\"script\"), s=d.getElementsByTagName(\"script\")[0]; g.type=\"text/javascript\";\ng.defer=true; g.async=true; g.src=u+\"piwik.js\"; s.parentNode.insertBefore(g,s);\n})();\n\n\n\n\n\n\n\n\nvar iam_data = {\n\"mg\":\"yes\",\n\"cp\":DartIvwKategorie,\n\"st\":\"berlin\",\n\"sv\":(location.pathname==\"/\"?\"ke\":\"in\"),\n\"co\":location.hostname\n}\niom.c(iam_data,1);\n\n\n\n\n"}, "geometry": {"type": "Point", "coordinates": [13.4429556, 52.514678]}}]}