{"type": "FeatureCollection", "features": [{"geometry": {"type": "Point", "coordinates": [13.226944, 52.561944]}, "type": "Feature", "properties": {"ausschuss": "Kultur", "bezirk": "Friedrichshain-Kreuzberg", "address": "", "title": "Konzept zur Durchf\u00fchrung der Gedenktage im Zusammenhang mit dem NS\n", "url": null, "date": null, "typ": null, "text": "\n\n\n\n\nDie Bezirksverordnetenversammlung m\u00f6ge beschlie\u00dfen:\u00a0Das Bezirksamt wird beauftragt ein Gedenkkonzept analog der Drucksache 29 f\u00fcr den 9. November (Novemberpogrome) f\u00fcr die drei anderen Gedenktage, dem 27. 1. (Tag der Befreiung von Ausschwitz), dem 8. Mai (Tag der Befreiung) und dem 1. September (\u00dcberfall auf Polen, Beginn des II. Weltkrieges) zu erarbeiten. Die jeweiligen Veranstaltungen\u00a0 sollen in Zusammenarbeit mit Schulen\u00a0 oder Jugendeinrichtungen unter Beteiligung der VVN entwickelt und durchgef\u00fchrt werden.\u00a0Begr\u00fcndung:Die Gedenktage k\u00f6nnen Anlass sein sich an den Bildungseinrichtungen mit den Verbrechen des NS im Rahmen eines Projektes gezielt auseinanderzusetzen. Das Ergebnis wertet die jeweiligen Veranstaltungen auf. \u00a0\u00a0BVV 25.03.2015Die Bezirksverordnetenversammlung beschlie\u00dft:\u00a0\u00dcberweisung: Ausschuss f\u00fcr Kultur und Bildung\u00a0\n\n\n/*<![CDATA[*/\nif (typeof DartIvwKategorie !== \"string\") window.DartIvwKategorie = \"boUndefined\";\n\nvar CP = \"//boss.berlinonline.de/cp.php?a=berlin&amp;r=\"+escape(document.referrer)+\"&amp;cat=\"+DartIvwKategorie+\"&amp;p=\"+escape(document.location)+\"&amp;d=\"+(Math.random()*100000);\ndocument.write(\"<img src=\\\"\"+CP+\"\\\" width=\\\"1\\\" height=\\\"1\\\" alt=\\\"\\\" id=\\\"cp_pixel\\\" style=\\\"position:absolute;width:1px;height:1px;\\\"/>\");\n/*]]>*/\n\n\n\n\nvar _paq = _paq || [];\n_paq.push([\"setDocumentTitle\", document.domain + \"/\" + document.title]);\n_paq.push([\"setCustomVariable\",1,\"Dart.active\",(typeof DartActive == \"boolean\" ? \"y\" : \"n\"),\"page\"]);\n_paq.push([\"trackPageView\"]);\n_paq.push([\"enableLinkTracking\"]);\n(function() {\nvar u=((\"https:\" == document.location.protocol) ? \"https\" : \"http\") + \"://piwik.berlinonline.de/\";\n_paq.push([\"setTrackerUrl\", u+\"piwik.php\"]);\n_paq.push([\"setSiteId\", \"1\"]);\nvar d=document, g=d.createElement(\"script\"), s=d.getElementsByTagName(\"script\")[0]; g.type=\"text/javascript\";\ng.defer=true; g.async=true; g.src=u+\"piwik.js\"; s.parentNode.insertBefore(g,s);\n})();\n\n\n\n\n\n\n\n\nvar iam_data = {\n\"mg\":\"yes\",\n\"cp\":DartIvwKategorie,\n\"st\":\"berlin\",\n\"sv\":(location.pathname==\"/\"?\"ke\":\"in\"),\n\"co\":location.hostname\n}\niom.c(iam_data,1);\n\n\n\n\n", "dsnr": "DS-1600-IV"}}]}