{"type": "FeatureCollection", "features": [{"type": "Feature", "properties": {"url": null, "title": "Information Anschutz Entertainmentcenter\n", "bezirk": "Friedrichshain-Kreuzberg", "typ": null, "date": null, "dsnr": "DS-1791-IV", "ausschuss": "Stadtentwicklung", "address": "", "text": "\n\n\n\n\nDie Bezirksverordnetenversammlung m\u00f6ge beschlie\u00dfen:\u00a0Das Bezirksamt wird beauftragt die Firma Anschutz Entertainment Group aufzufordern, ihr Bauvorhaben Anschutz Entertainmentcenter sowie den aktuellen Stand der gesamten Grundst\u00fccksentwicklung in einer \u00f6ffentlichen B\u00fcrgerveranstaltung orts- und zeitnah vorzustellen.Begr\u00fcndungDie Vertreter der Anschutz Entertainment Group sind bereits zwei Mal nicht zur eingeladenen Vorstellung der Planungen Anschutz Entertainmentcenter im Ausschuss StadtQM erschienen. Dies muss dringend nachgeholt werden sowie die \u00d6ffentlichkeit informiert werden.\u00a0\u00a0Die Piratenfraktion Friedrichshain-Kreuzberg entl\u00e4sst diesen Text\u00a0 in die Gemeinfreiheit (Public Domain) als CC-0\u00a0 (http://creativecommons.org/publicdomain/zero/1.0/legalcode). Sie\u00a0 verzichtet weltweit auf alle urheberrechtlichen und verwandten\u00a0 Schutzrechte, soweit dies gesetzlich m\u00f6glich ist. Der Antragstext darf\u00a0 ohne weitere Erlaubnis kopiert, ver\u00e4ndert, verbreitet und aufgef\u00fchrt\u00a0 werden. Dies schliesst kommerzielle Zwecke explizit mit ein.\u00a0\u00a0StadtQM 08.07.2015Die Bezirksverordnetenversammlung m\u00f6ge beschlie\u00dfen:\u00a0Das Bezirksamt wird beauftragt die Firma Anschutz Entertainment Group aufzufordern, ihr Bauvorhaben Anschutz Entertainmentcenter sowie den aktuellen Stand der gesamten Grundst\u00fccksentwicklung in einer \u00f6ffentlichen B\u00fcrgerveranstaltung orts- und zeitnah vorzustellen.\u00a0\u00a0BVV 15.07.2015Die Bezirksverordnetenversammlung beschlie\u00dft:\u00a0Das Bezirksamt wird beauftragt die Firma Anschutz Entertainment Group aufzufordern, ihr Bauvorhaben Anschutz Entertainmentcenter sowie den aktuellen Stand der gesamten Grundst\u00fccksentwicklung in einer \u00f6ffentlichen B\u00fcrgerveranstaltung orts- und zeitnah vorzustellen.\u00a0\u00a0\n\n\n/*<![CDATA[*/\nif (typeof DartIvwKategorie !== \"string\") window.DartIvwKategorie = \"boUndefined\";\n\nvar CP = \"//boss.berlinonline.de/cp.php?a=berlin&amp;r=\"+escape(document.referrer)+\"&amp;cat=\"+DartIvwKategorie+\"&amp;p=\"+escape(document.location)+\"&amp;d=\"+(Math.random()*100000);\ndocument.write(\"<img src=\\\"\"+CP+\"\\\" width=\\\"1\\\" height=\\\"1\\\" alt=\\\"\\\" id=\\\"cp_pixel\\\" style=\\\"position:absolute;width:1px;height:1px;\\\"/>\");\n/*]]>*/\n\n\n\n\nvar _paq = _paq || [];\n_paq.push([\"setDocumentTitle\", document.domain + \"/\" + document.title]);\n_paq.push([\"setCustomVariable\",1,\"Dart.active\",(typeof DartActive == \"boolean\" ? \"y\" : \"n\"),\"page\"]);\n_paq.push([\"trackPageView\"]);\n_paq.push([\"enableLinkTracking\"]);\n(function() {\nvar u=((\"https:\" == document.location.protocol) ? \"https\" : \"http\") + \"://piwik.berlinonline.de/\";\n_paq.push([\"setTrackerUrl\", u+\"piwik.php\"]);\n_paq.push([\"setSiteId\", \"1\"]);\nvar d=document, g=d.createElement(\"script\"), s=d.getElementsByTagName(\"script\")[0]; g.type=\"text/javascript\";\ng.defer=true; g.async=true; g.src=u+\"piwik.js\"; s.parentNode.insertBefore(g,s);\n})();\n\n\n\n\n\n\n\n\nvar iam_data = {\n\"mg\":\"yes\",\n\"cp\":DartIvwKategorie,\n\"st\":\"berlin\",\n\"sv\":(location.pathname==\"/\"?\"ke\":\"in\"),\n\"co\":location.hostname\n}\niom.c(iam_data,1);\n\n\n\n\n"}, "geometry": {"type": "Point", "coordinates": [13.226944, 52.561944]}}]}