{"type": "FeatureCollection", "features": [{"geometry": {"type": "Point", "coordinates": [13.226944, 52.561944]}, "type": "Feature", "properties": {"ausschuss": "Personal; Kultur", "bezirk": "Friedrichshain-Kreuzberg", "address": "", "title": "Erhalt der Bona-Peiser-Bibliothek\n", "url": null, "date": null, "typ": null, "text": "\n\n\n\n\nDie Bezirksverordnetenversammlung m\u00f6ge beschlie\u00dfen:\u00a0In die Drucksache DS/1161/IV wird folgender zweiter Absatz eingef\u00fcgt.\u00a0Zus\u00e4tzlich wird das Bezirksamt beauftragt zu pr\u00fcfen, welche Alternativen zum im Bezirksamt vereinbarten linearen Personalabbau \u00fcber alle \u00c4mter und Abteilungen bestehen. Dabei ist insbesondere der Berichtsauftrag der BVV aus dem letzten Jahr zu bearbeiten, in dem verlangt wurde, eine \u00dcbertragung von Aufgaben des bezirklichen Immobilienservice auf die landeseigene Berlin Immobilien Management (BIM) zu pr\u00fcfen. Bis zur Vorlage diese Pr\u00fcfungsergebnisses, welches mit gro\u00dfer Wahrscheinlichkeit auch Aussagen zur Personalentwicklung im Immobilienbereich beinhaltet, sind keine weiteren Entscheidungen bez\u00fcglich der Bibliothek zu treffen.\u00a0\u00a0PHI, KuBi 01.07.2014\u00a0Die Drucksache wird von der antragstellenden Fraktion zur\u00fcckgezogen.\n\n\n/*<![CDATA[*/\nif (typeof DartIvwKategorie !== \"string\") window.DartIvwKategorie = \"boUndefined\";\n\nvar CP = \"//boss.berlinonline.de/cp.php?a=berlin&amp;r=\"+escape(document.referrer)+\"&amp;cat=\"+DartIvwKategorie+\"&amp;p=\"+escape(document.location)+\"&amp;d=\"+(Math.random()*100000);\ndocument.write(\"<img src=\\\"\"+CP+\"\\\" width=\\\"1\\\" height=\\\"1\\\" alt=\\\"\\\" id=\\\"cp_pixel\\\" style=\\\"position:absolute;width:1px;height:1px;\\\"/>\");\n/*]]>*/\n\n\n\n\nvar _paq = _paq || [];\n_paq.push([\"setDocumentTitle\", document.domain + \"/\" + document.title]);\n_paq.push([\"setCustomVariable\",1,\"Dart.active\",(typeof DartActive == \"boolean\" ? \"y\" : \"n\"),\"page\"]);\n_paq.push([\"trackPageView\"]);\n_paq.push([\"enableLinkTracking\"]);\n(function() {\nvar u=((\"https:\" == document.location.protocol) ? \"https\" : \"http\") + \"://piwik.berlinonline.de/\";\n_paq.push([\"setTrackerUrl\", u+\"piwik.php\"]);\n_paq.push([\"setSiteId\", \"1\"]);\nvar d=document, g=d.createElement(\"script\"), s=d.getElementsByTagName(\"script\")[0]; g.type=\"text/javascript\";\ng.defer=true; g.async=true; g.src=u+\"piwik.js\"; s.parentNode.insertBefore(g,s);\n})();\n\n\n\n\n\n\n\n\nvar iam_data = {\n\"mg\":\"yes\",\n\"cp\":DartIvwKategorie,\n\"st\":\"berlin\",\n\"sv\":(location.pathname==\"/\"?\"ke\":\"in\"),\n\"co\":location.hostname\n}\niom.c(iam_data,1);\n\n\n\n\n", "dsnr": "DS-1161-01-IV"}}]}