{"type": "FeatureCollection", "features": [{"geometry": {"type": "Point", "coordinates": [13.226944, 52.561944]}, "type": "Feature", "properties": {"ausschuss": "Migration; Personal", "bezirk": "Friedrichshain-Kreuzberg", "address": "", "title": "Keine Rechtsmittel und zivilrechtlichen Schritte gegen den Beschluss des Berliner Verwaltungsgerichts bzw. die Gefl\u00fcchteten in der ehemaligen Gerhart-Hauptmann-Schule\n", "url": null, "date": null, "typ": null, "text": "\n\n\n\n\nDie Bezirksverordnetenversammlung m\u00f6ge beschlie\u00dfen:\u00a0Das Bezirksamt wird aufgefordert, keine Rechtsmittel gegen den Beschluss des Verwaltungsgerichts Berlin, vom 22. Mai 2015, einzulegen und die Beschwerde beim Oberverwaltungsgericht Berlin-Brandenburg zur\u00fcckzuziehen. Dar\u00fcber hinaus wird das Bezirksamt aufgefordert, keine zivilrechtlichen Schritte gegen die verbliebenen Gefl\u00fcchteten in der ehemaligen Gerhart-Hauptmann-Schule einzuleiten, die auf einen R\u00e4umungstitel abzielen, und sich auf eine einvernehmliche Verhandlungsl\u00f6sung zu konzentrieren.\u00a0Begr\u00fcndung:\u00a0Das Bezirksamt ist bei seinem Versuch die ehemalige Gerhart-Hauptmann-Schule in Kreuzberg r\u00e4umen zu lassen vor dem Verwaltungsgericht gescheitert. Nach Ansicht der 1. Kammer des Gerichts, hat der Bezirk mit den Bewohner*innen der Schule eine Art zivilrechtliche Vereinbarung getroffen.\u00a0Ende Juni 2014 hatte Baustadtrat Hans Panhoff (B\u00fcndnis 90/Die Gr\u00fcnen) schon einmal versucht die Schule r\u00e4umen zu lassen. W\u00e4hrend des folgenden Gro\u00dfeinsatzes der Polizei wurde der Kiez um die Gerhart-Hauptmann-Schule tagelang von bis zu 900 Polizist*innen belagert, um 40 Fl\u00fcchtlingsaktivist*innen zum Verlassen der Schule zu bewegen. Nach neun Tagen schlossen Bezirksamt und Gefl\u00fcchtete am 1. Juli eine Vereinbarung, die u.a. vorsah, dass die verbliebenen Bewohner*innen in der Schule bleiben k\u00f6nnen, wenn sie sich in einen Fl\u00fcgel der Schule zur\u00fcckziehen, an den Aufr\u00e4umarbeiten beteiligen und sich bereit erkl\u00e4ren, einen privaten Sicherheitsdienst zu akzeptieren. \u00a0Entsprechend mehrerer Beschl\u00fcsse der BVV und dem Umsetzungsbericht des Bezirksamts vom 3.6.2014 ist ein Umbau der ehemaligen Schule in ein internationales Fl\u00fcchtlingszentrum unter der Beteiligung der Bewohner*innen anzustreben. Das Bezirksamt hat gegen das Urteil des Berliner Verwaltungsgerichts, vom 22. Mai 2015, Beschwerde beim Oberverwaltungsgericht Berlin-Brandenburg eingelegt. Doch statt immer wieder gerichtlich gegen die Bewohner*innen vorzugehen, sollte das Bezirksamt besser seine Zusagen umsetzen und endlich mit der Entwicklung und dem Bau des internationalen Fl\u00fcchtlingszentrums in der ehemaligen Gerhart-Hauptmann-Schule unter Beteiligung der Gefl\u00fcchteten beginnen.\u00a0\u00a0BVV 24.06.2015Die Bezirksverordnetenversammlung beschlie\u00dft:\u00a0\u00dcberweisung: Integrationsausschuss - Ausschuss f\u00fcr Migration, Teilhabe und Chancengleichheit, Ausschuss f\u00fcr Personal, Haushalt und Investitionen, Rechnungspr\u00fcfung (federf\u00fchrend)\u00a0\u00a0PHI 14.07.2015Die Bezirksverordnetenversammlung m\u00f6ge beschlie\u00dfen:\u00a0Der Antrag wird abgelehnt.\u00a0\u00a0PHI 15.07.2015Die Bezirksverordnetenversammlung beschlie\u00dft:\u00a0Der Antrag wird abgelehnt.\u00a0\n\n\n/*<![CDATA[*/\nif (typeof DartIvwKategorie !== \"string\") window.DartIvwKategorie = \"boUndefined\";\n\nvar CP = \"//boss.berlinonline.de/cp.php?a=berlin&amp;r=\"+escape(document.referrer)+\"&amp;cat=\"+DartIvwKategorie+\"&amp;p=\"+escape(document.location)+\"&amp;d=\"+(Math.random()*100000);\ndocument.write(\"<img src=\\\"\"+CP+\"\\\" width=\\\"1\\\" height=\\\"1\\\" alt=\\\"\\\" id=\\\"cp_pixel\\\" style=\\\"position:absolute;width:1px;height:1px;\\\"/>\");\n/*]]>*/\n\n\n\n\nvar _paq = _paq || [];\n_paq.push([\"setDocumentTitle\", document.domain + \"/\" + document.title]);\n_paq.push([\"setCustomVariable\",1,\"Dart.active\",(typeof DartActive == \"boolean\" ? \"y\" : \"n\"),\"page\"]);\n_paq.push([\"trackPageView\"]);\n_paq.push([\"enableLinkTracking\"]);\n(function() {\nvar u=((\"https:\" == document.location.protocol) ? \"https\" : \"http\") + \"://piwik.berlinonline.de/\";\n_paq.push([\"setTrackerUrl\", u+\"piwik.php\"]);\n_paq.push([\"setSiteId\", \"1\"]);\nvar d=document, g=d.createElement(\"script\"), s=d.getElementsByTagName(\"script\")[0]; g.type=\"text/javascript\";\ng.defer=true; g.async=true; g.src=u+\"piwik.js\"; s.parentNode.insertBefore(g,s);\n})();\n\n\n\n\n\n\n\n\nvar iam_data = {\n\"mg\":\"yes\",\n\"cp\":DartIvwKategorie,\n\"st\":\"berlin\",\n\"sv\":(location.pathname==\"/\"?\"ke\":\"in\"),\n\"co\":location.hostname\n}\niom.c(iam_data,1);\n\n\n\n\n", "dsnr": "DS-1759-IV"}}]}