{"type": "FeatureCollection", "features": [{"geometry": {"type": "Point", "coordinates": [13.226944, 52.561944]}, "type": "Feature", "properties": {"ausschuss": "", "bezirk": "Friedrichshain-Kreuzberg", "address": "", "title": "Zukunft des internationalen Fl\u00fcchtlingszentrums und Vereinbarung mit den Bewohner*innen der Gerhart-Hauptmann-Schule (GHS)\n", "url": null, "date": null, "typ": null, "text": "\n\n\n\n\nIch frage das Bezirksamt:\u00a0Hat das Bezirksamt von seinen Planungen, ein internationales Fl\u00fcchtlingszentrum in der ehemaligen Gerhart-Hauptmann-Schule einzurichten, Abstand genommen?\u00a0Wann k\u00f6nnen die Fraktionen mit der Einberufung der fraktions\u00fcbergreifenden Arbeitsgruppe zur Konzeptionierung des internationalen Fl\u00fcchtlingszentrums rechnen?\u00a0Wann und mit wem hat das Bezirksamt verhandelt, beziehungsweise gesprochen, bei der Suche nach einem potentiellen Tr\u00e4ger f\u00fcr das internationale Fl\u00fcchtlingszentrum?\u00a0\u00a0\u00a0Zusammengefasst und beantwortet in der Drucksache DS/1359/IV.\u00a0\n\n\n/*<![CDATA[*/\nif (typeof DartIvwKategorie !== \"string\") window.DartIvwKategorie = \"boUndefined\";\n\nvar CP = \"//boss.berlinonline.de/cp.php?a=berlin&amp;r=\"+escape(document.referrer)+\"&amp;cat=\"+DartIvwKategorie+\"&amp;p=\"+escape(document.location)+\"&amp;d=\"+(Math.random()*100000);\ndocument.write(\"<img src=\\\"\"+CP+\"\\\" width=\\\"1\\\" height=\\\"1\\\" alt=\\\"\\\" id=\\\"cp_pixel\\\" style=\\\"position:absolute;width:1px;height:1px;\\\"/>\");\n/*]]>*/\n\n\n\n\nvar _paq = _paq || [];\n_paq.push([\"setDocumentTitle\", document.domain + \"/\" + document.title]);\n_paq.push([\"setCustomVariable\",1,\"Dart.active\",(typeof DartActive == \"boolean\" ? \"y\" : \"n\"),\"page\"]);\n_paq.push([\"trackPageView\"]);\n_paq.push([\"enableLinkTracking\"]);\n(function() {\nvar u=((\"https:\" == document.location.protocol) ? \"https\" : \"http\") + \"://piwik.berlinonline.de/\";\n_paq.push([\"setTrackerUrl\", u+\"piwik.php\"]);\n_paq.push([\"setSiteId\", \"1\"]);\nvar d=document, g=d.createElement(\"script\"), s=d.getElementsByTagName(\"script\")[0]; g.type=\"text/javascript\";\ng.defer=true; g.async=true; g.src=u+\"piwik.js\"; s.parentNode.insertBefore(g,s);\n})();\n\n\n\n\n\n\n\n\nvar iam_data = {\n\"mg\":\"yes\",\n\"cp\":DartIvwKategorie,\n\"st\":\"berlin\",\n\"sv\":(location.pathname==\"/\"?\"ke\":\"in\"),\n\"co\":location.hostname\n}\niom.c(iam_data,1);\n\n\n\n\n", "dsnr": "DS-1336-IV"}}]}