{"type": "FeatureCollection", "features": [{"geometry": {"type": "Point", "coordinates": [13.226944, 52.561944]}, "type": "Feature", "properties": {"ausschuss": "Kultur", "bezirk": "Friedrichshain-Kreuzberg", "address": "", "title": "Ausstellung \"Der Weg zur deutschen Einheit\" \n", "url": null, "date": null, "typ": null, "text": "\n\n\n\n\nDie Bezirksverordnetenversammlung m\u00f6ge beschlie\u00dfen:\u00a0Das Bezirksamt wird beauftragt zu pr\u00fcfen, die Ausstellung \"Der Weg zur deutschen Einheit\" der Bundesstiftung zur Aufarbeitung der SED-Diktatur f\u00fcr das Jahr 2015 im Rathaus Kreuzberg zu pr\u00e4sentieren.\u00a0Begr\u00fcndung:\u00a0Am 3. Oktober 1990 wurde Deutschland wiedervereinigt und die Teilung beendet.Dieses f\u00fcr das deutsche Volk gl\u00fcckliche Ereignis kam nicht von ungef\u00e4hr, sondern bedurfte vieler innen- und au\u00dfenpolitischer Weichenstellungen. Die Ausstellung \"Der Weg zur deutschen Einheit\" rekonstruiert mit 20 DIN A1 Plakaten diese innen- und au\u00dfenpolitischen Weichenstellungen.Die Ausstellung ist damit ein gutes Medium, um an einem \u00f6ffentlichen Ort wie dem Rathaus Kreuzberg eine Auseinandersetzung mit der Geschichte der deutschen Einheit anzuregen. Autor und Kurator der Ausstellung ist der Historiker Dr. Ulrich M\u00e4hlert, der in der Bundesstiftung zur Aufarbeitung der SED-Diktatur den Arbeitsbereich Wissenschaft leitet.\u00a0\u00a0BVV 17.12.2014Die Bezirksverordnetenversammlung beschlie\u00dft:\u00a0\u00dcberweisung: Ausschuss f\u00fcr Kultur und Bildung \u00a0\u00a0KuBi 06.01.2015Die Bezirksverordnetenversammlung m\u00f6ge beschlie\u00dfen:\u00a0Der Antrag wird abgelehnt.\u00a0\u00a0BVV 28.01.2015Die Bezirksverordnetenversammlung beschlie\u00dft:\u00a0Das Bezirksamt wird beauftragt, die Ausstellung \"Der Weg zur deutschen Einheit\" der Bundesstiftung zur Aufarbeitung der SED-Diktatur f\u00fcr das Jahr 2015 im Rathaus Kreuzberg zu pr\u00e4sentieren.\u00a0\u00a0Die Bezirksverordnetenversammlung m\u00f6ge beschlie\u00dfen:\u00a0Die Vorlage wird zur Kenntnis genommen. \u00a0\u00a025.11.2015 Die Bezirksverordnetenversammlung beschlie\u00dft:\u00a0\u00dcberweisung: Ausschuss f\u00fcr Kultur und Bildung\u00a0\u00a0KuBi 03.12.2015Die Bezirksverordnetenversammlung m\u00f6ge beschlie\u00dfen:\u00a0Die Vorlage wird zur Kenntnis genommen. \u00a0\u00a0BVV 16.12.2015 Die Bezirksverordnetenversammlung beschlie\u00dft:\u00a0Die Vorlage wird zur Kenntnis genommen. \u00a0\n\n\n/*<![CDATA[*/\nif (typeof DartIvwKategorie !== \"string\") window.DartIvwKategorie = \"boUndefined\";\n\nvar CP = \"//boss.berlinonline.de/cp.php?a=berlin&amp;r=\"+escape(document.referrer)+\"&amp;cat=\"+DartIvwKategorie+\"&amp;p=\"+escape(document.location)+\"&amp;d=\"+(Math.random()*100000);\ndocument.write(\"<img src=\\\"\"+CP+\"\\\" width=\\\"1\\\" height=\\\"1\\\" alt=\\\"\\\" id=\\\"cp_pixel\\\" style=\\\"position:absolute;width:1px;height:1px;\\\"/>\");\n/*]]>*/\n\n\n\n\nvar _paq = _paq || [];\n_paq.push([\"setDocumentTitle\", document.domain + \"/\" + document.title]);\n_paq.push([\"setCustomVariable\",1,\"Dart.active\",(typeof DartActive == \"boolean\" ? \"y\" : \"n\"),\"page\"]);\n_paq.push([\"trackPageView\"]);\n_paq.push([\"enableLinkTracking\"]);\n(function() {\nvar u=((\"https:\" == document.location.protocol) ? \"https\" : \"http\") + \"://piwik.berlinonline.de/\";\n_paq.push([\"setTrackerUrl\", u+\"piwik.php\"]);\n_paq.push([\"setSiteId\", \"1\"]);\nvar d=document, g=d.createElement(\"script\"), s=d.getElementsByTagName(\"script\")[0]; g.type=\"text/javascript\";\ng.defer=true; g.async=true; g.src=u+\"piwik.js\"; s.parentNode.insertBefore(g,s);\n})();\n\n\n\n\n\n\n\n\nvar iam_data = {\n\"mg\":\"yes\",\n\"cp\":DartIvwKategorie,\n\"st\":\"berlin\",\n\"sv\":(location.pathname==\"/\"?\"ke\":\"in\"),\n\"co\":location.hostname\n}\niom.c(iam_data,1);\n\n\n\n\n", "dsnr": "DS-1453-IV"}}]}