{"type": "FeatureCollection", "features": [{"geometry": {"type": "Point", "coordinates": [13.226944, 52.561944]}, "type": "Feature", "properties": {"ausschuss": "", "bezirk": "Friedrichshain-Kreuzberg", "address": "", "title": "Uferwanderweg Stralauer Halbinsel\n", "url": null, "date": null, "typ": null, "text": "\n\n\n\n\n\n\nWie ist\nder aktuelle Sachstand bez\u00fcglich der angestrebten Durchg\u00e4ngigkeit des\nUferwanderweges auf der Spreeseite der Halbinsel Stralau?\n\u00a0\nBezirksamt Friedrichshain-Kreuzberg von Berlin\u00a0\u00a0\u00a0\u00a0\u00a0\u00a0\u00a0\u00a0\u00a0\u00a0\u00a0\u00a0\u00a0\u00a0\u00a0\u00a0\u00a0\u00a0\u00a0\u00a0\u00a0\u00a0\u00a0\u00a0\u00a0\u00a0\u00a0\u00a0\u00a0\u00a0\u00a0\u00a0\u00a0\u00a0\u00a0\u00a0\u00a0\u00a0\u00a0\u00a0\u00a0\u00a0\u00a0\u00a0\u00a0\u00a0\u00a0\u00a0\u00a0\u00a0\u00a0\u00a0\u00a0 15.06.07\nAbt. Stadtentwicklung und Bauen\u00a0\u00a0\u00a0\u00a0\u00a0\u00a0\u00a0\u00a0\u00a0\u00a0\u00a0\u00a0\u00a0\u00a0\u00a0\u00a0\u00a0\u00a0\u00a0\u00a0\u00a0\u00a0\u00a0\u00a0\u00a0\u00a0\u00a0\u00a0\u00a0\u00a0\u00a0\u00a0\u00a0\u00a0\u00a0\u00a0\u00a0\u00a0\u00a0\u00a0\u00a0\u00a0\u00a0\u00a0\u00a0\u00a0\u00a0\u00a0\u00a0\u00a0\u00a0\u00a0\u00a0\u00a0\u00a0\u00a0\u00a0\u00a0\u00a0\u00a0\u00a0\u00a0\u00a0\u00a0\u00a0\u00a0\u00a0\u00a0\u00a0\u00a0\u00a0\u00a0\u00a0\u00a0\u00a0\u00a0\u00a0\u00a0 \n- 3260 \u2013\nStadtrat\n\u00a0\n\u00a0\n\u00a0\n\u00a0\n\u00a0\nHerrn\nAndy Hehmke\nBezirksverordneten\n\u00a0\n\u00fcber\n\u00a0\nHerrn\nBezirksverordnetenvorsteher\nRiza Baran\n\n\n\n\n\n\n\n\n\n\n\u00a0\n\u00a0\n\nSchriftliche Beantwortung der M\u00fcndlichen Anfrage Nr.\n1974/II \u2013 Uferwanderweg Stralauer Halbinsel \n\u00a0\n\u00a0\n\u00a0\nSehr\ngeehrter Herr Hehmke,\n\u00a0\nIhre o.g.\nM\u00fcndliche Anfrage vom\u00a0 21.02.2006\nbeantworte ich wie folgt:\n\u00a0\nFrage: \nWie ist der aktuelle Sachstand bez\u00fcglich der angestrebten\nDurchg\u00e4ngigkeit des Uferwanderweges auf der Spreeseite der Halbinsel Stralau?\n\u00a0\nAntwort: \nAbgesehen von den beiden Grundst\u00fccken Alt-Stralau 23\n(Eigent\u00fcmer: Herr Dr. Walter Kracht) und Alt Stralau 29 (Eigent\u00fcmer: Herr\nMichael Stalherm) verf\u00fcgt die Wasserstadt GmbH \u00fcber alle Grundst\u00fccke bzw.\nGrundst\u00fccksteilfl\u00e4chen auf der Halbinsel Stralau, f\u00fcr die die\nEntwicklungsplanung den Bau eines \u00f6ffentlichen Ufergr\u00fcnzugs mit integriertem\nWanderweg vorsieht.\nAu\u00dfer Betracht bleibt hierbei das Grundst\u00fcck Alt-Stralau\n5-11: der Friedhof wurde seinerzeit auf Wunsch der evangelischen\nKirchengemeinde Zwingli-Stralau nicht in den Entwicklungsbereich einbezogen.\nDeshalb war und ist hier auch kein \u00f6ffentlicher Ufergr\u00fcnzug vorgesehen.\nAlt-Stralau 23: zur Zeit steht der Enteignungsantrag der Wasserstadt vor\nder Entscheidung der Enteignungsbeh\u00f6rde.\nAlt-Stralau 29: Das Gutachten des Gutachterausschusses \u00fcber den Bodenwert\nist der Ent\u00adeignungsbeh\u00f6rde unl\u00e4ngst zugeleitet worden. Die Enteignungsbeh\u00f6rde\nhat die Befassung mit dem Enteignungsantrag der Wasserstadt GmbH in den\nn\u00e4chsten Wochen in Aussicht gestellt.\n\u00a0\nMit freundlichen Gr\u00fc\u00dfen\n\u00a0\n\u00a0\n\u00a0\n\u00a0\n\u00a0\nFranz Schulz\nDez StadtBau\n\u00a0\n\n\n\n\n/*<![CDATA[*/\nif (typeof DartIvwKategorie !== \"string\") window.DartIvwKategorie = \"boUndefined\";\n\nvar CP = \"//boss.berlinonline.de/cp.php?a=berlin&amp;r=\"+escape(document.referrer)+\"&amp;cat=\"+DartIvwKategorie+\"&amp;p=\"+escape(document.location)+\"&amp;d=\"+(Math.random()*100000);\ndocument.write(\"<img src=\\\"\"+CP+\"\\\" width=\\\"1\\\" height=\\\"1\\\" alt=\\\"\\\" id=\\\"cp_pixel\\\" style=\\\"position:absolute;width:1px;height:1px;\\\"/>\");\n/*]]>*/\n\n\n\n\nvar _paq = _paq || [];\n_paq.push([\"setDocumentTitle\", document.domain + \"/\" + document.title]);\n_paq.push([\"setCustomVariable\",1,\"Dart.active\",(typeof DartActive == \"boolean\" ? \"y\" : \"n\"),\"page\"]);\n_paq.push([\"trackPageView\"]);\n_paq.push([\"enableLinkTracking\"]);\n(function() {\nvar u=((\"https:\" == document.location.protocol) ? \"https\" : \"http\") + \"://piwik.berlinonline.de/\";\n_paq.push([\"setTrackerUrl\", u+\"piwik.php\"]);\n_paq.push([\"setSiteId\", \"1\"]);\nvar d=document, g=d.createElement(\"script\"), s=d.getElementsByTagName(\"script\")[0]; g.type=\"text/javascript\";\ng.defer=true; g.async=true; g.src=u+\"piwik.js\"; s.parentNode.insertBefore(g,s);\n})();\n\n\n\n\n\n\n\n\nvar iam_data = {\n\"mg\":\"yes\",\n\"cp\":DartIvwKategorie,\n\"st\":\"berlin\",\n\"sv\":(location.pathname==\"/\"?\"ke\":\"in\"),\n\"co\":location.hostname\n}\niom.c(iam_data,1);\n\n\n\n\n", "dsnr": "DS-1974-II"}}]}