{"type": "FeatureCollection", "features": [{"type": "Feature", "properties": {"url": null, "title": "Unterbringung von Bewohner*innen der Gerhart-Hauptmann-Schule\n", "bezirk": "Friedrichshain-Kreuzberg", "typ": null, "date": null, "dsnr": "DS-1263-IV", "ausschuss": "", "address": "", "text": "\n\n\n\n\nDie Bezirksverordnetenversammlung m\u00f6ge beschlie\u00dfen:\u00a0Das Bezirksamt wird aufgefordert sich bei der Senatsverwaltung daf\u00fcr einzusetzen, dass den Bewohner*innen der Gerhart-Hauptmann-Schule, denen in der letzten Woche kein Platz in einer Sammelunterkunft organisiert werden konnte und die sich nicht bis heute in der besetzten Schule aufhalten, eine Unterbringungsm\u00f6glichkeit zur Verf\u00fcgung gestellt wird.\u00a0Begr\u00fcndung:Nach wie vor gibt es Menschen die in der besetzten Gerhart-Hauptmann-Schule gelebt haben, denen aber in der Folge der R\u00e4umung keine Unterbringungsm\u00f6glichkeit gestellt wurden. Es muss sichergestellt werden, dass auch diese Personengruppe umgehend mit Unterbringungsm\u00f6glichkeiten versorgt wird, da die meisten von ihnen zur Zeit von Obdachlosigkeit betroffen sind.\u00a0\u00a0\u00c4R 26.08.2014Die Drucksache hat sich durch die BVV am 08. Juli erledigt und wird zur\u00fcckgezogen.\u00a0\n\n\n/*<![CDATA[*/\nif (typeof DartIvwKategorie !== \"string\") window.DartIvwKategorie = \"boUndefined\";\n\nvar CP = \"//boss.berlinonline.de/cp.php?a=berlin&amp;r=\"+escape(document.referrer)+\"&amp;cat=\"+DartIvwKategorie+\"&amp;p=\"+escape(document.location)+\"&amp;d=\"+(Math.random()*100000);\ndocument.write(\"<img src=\\\"\"+CP+\"\\\" width=\\\"1\\\" height=\\\"1\\\" alt=\\\"\\\" id=\\\"cp_pixel\\\" style=\\\"position:absolute;width:1px;height:1px;\\\"/>\");\n/*]]>*/\n\n\n\n\nvar _paq = _paq || [];\n_paq.push([\"setDocumentTitle\", document.domain + \"/\" + document.title]);\n_paq.push([\"setCustomVariable\",1,\"Dart.active\",(typeof DartActive == \"boolean\" ? \"y\" : \"n\"),\"page\"]);\n_paq.push([\"trackPageView\"]);\n_paq.push([\"enableLinkTracking\"]);\n(function() {\nvar u=((\"https:\" == document.location.protocol) ? \"https\" : \"http\") + \"://piwik.berlinonline.de/\";\n_paq.push([\"setTrackerUrl\", u+\"piwik.php\"]);\n_paq.push([\"setSiteId\", \"1\"]);\nvar d=document, g=d.createElement(\"script\"), s=d.getElementsByTagName(\"script\")[0]; g.type=\"text/javascript\";\ng.defer=true; g.async=true; g.src=u+\"piwik.js\"; s.parentNode.insertBefore(g,s);\n})();\n\n\n\n\n\n\n\n\nvar iam_data = {\n\"mg\":\"yes\",\n\"cp\":DartIvwKategorie,\n\"st\":\"berlin\",\n\"sv\":(location.pathname==\"/\"?\"ke\":\"in\"),\n\"co\":location.hostname\n}\niom.c(iam_data,1);\n\n\n\n\n"}, "geometry": {"type": "Point", "coordinates": [13.226944, 52.561944]}}]}