{"type": "FeatureCollection", "features": [{"geometry": {"type": "Point", "coordinates": [13.226944, 52.561944]}, "type": "Feature", "properties": {"ausschuss": "", "bezirk": "Friedrichshain-Kreuzberg", "address": "", "title": "Wachschutz an Schulen\n", "url": null, "date": null, "typ": null, "text": "\n\n\n\n\n\n\nIch frage das Bezirksamt:\n\u00a0\n\u00a0\n\nWurde oder wird mit welchen Aufgaben und an\n     welchen Schulen im Bezirk ein Wachschutz w\u00e4hrend der Schulzeit eingesetzt?\n\nWer hat die Entscheidung getroffen und wurde oder\n     wird die Schulkonferenz einbezogen? \nWie wird der Wachschutz finanziert? \n\n\u00a0\n\u00a0\n\u00a0\n\u00a0\n\n\n\n\n\u00a0\n\u00a0\n\u00a0\n\u00a0\n\u00a0\nErg\u00e4nzung zur\nM\u00fcndlichen Anfrage DS/0050/III\nBetr.: Wachschutz an Schulen\n\u00a0\nSehr geehrte Frau Seid,\n\u00a0\naufgrund Ihres m\u00fcndlichen Hinweises zur o. g. Anfrage\nm\u00f6chte ich zum Thema Aufsichts- und Sicherheitsdienste an Schulen nachfolgende\nErg\u00e4nzung vornehmen.\n\u00a0\nZu 1.: Wurde\noder wird mit welchen Aufgaben und an welchen Schulen im Bezirk ein Wachschutz \n\u00a0\u00a0\u00a0\u00a0\u00a0\u00a0\u00a0\u00a0\u00a0\nw\u00e4hrend der Schulzeit eingesetzt?\n\u00a0\nDer Projekttr\u00e4ger FORUM Arbeit und\nProjekte e. V. hat im Mai 2006 den Grundschulen des Bezirkes\nFriedrichshain-Kreuzberg in Abstimmung mit der Au\u00dfenstelle der Senatsverwaltung\nf\u00fcr Bildung, Wissenschaft und Forschung und dem Personalrat f\u00fcr Lehrer/innen\nund Erzieher/innen eine MAE-Ma\u00dfnahme im Bereich Aufsichts- und\nSicherheitsdienste zur Unterst\u00fctzung der Schulleiter/innen sowie der\nLehrer/innen und Erzieher/innen angeboten.\n\u00a0\nZu den Aufgaben der MAE-Kr\u00e4fte geh\u00f6ren:\n\u00a0\n- Pausenaufsicht, Schulhofaufsicht,\nKontrollg\u00e4nge, Schulwegbegleitung\n- Achten auf beg\u00fcnstigende Bedingungen f\u00fcr\nSt\u00f6rungen durch schulfremde Personen\n- Gewaltpr\u00e4vention \n- Unterst\u00fctzung bei schulischen\nVeranstaltungen\n- Deeskalation bei Gewaltkonflikten\n- ggf. Arbeit mit Sch\u00fclergruppen zum Thema\nGewaltpr\u00e4vention, Konfliktl\u00f6sung und Sicherheit.\n\u00a0\nVier Schulen \n\u00a0\n- Modersohn-Grundschule\n- Charlotte-Salomon-Grundschule\n- Lemgo-Grundschule und\n- Paul-Dohrmann-Grundschule\n\u00a0\nhaben einen Bedarf gemeldet und jeweils 3\nMAE-Kr\u00e4fte erhalten. \n\u00a0\n\u00a0\n\u00a0\n\u00a0\n\u00a0\nZu 2.: Wer hat\ndie Entscheidung getroffen und wurde oder wird die Schulkonferenz einbezogen?\n\u00a0\nDie Entscheidung bzw. Genehmigung der\nMa\u00dfnahme erfolgte von der Au\u00dfenstelle Friedrichshain-Kreuzberg der\nSenatsverwaltung f\u00fcr Bildung, Wissenschaft und Forschung.\nDie Information der Schulkonferenz erfolgt\nin der Verantwortung der Schulleiter/innen.\n\u00a0\n\u00a0\nZu 3.: Wie\nwird der Wachschutz finanziert? \n\u00a0\nDie Finanzierung erfolgt durch die\nBundesagentur f\u00fcr Arbeit, vertreten durch die Jobcenter. \n\u00a0\n\u00a0\nMit freundlichem Gru\u00df\n\u00a0\n\u00a0\n\u00a0\nM. Herrmann\nBezirksstadtr\u00e4tin \n\u00a0\n\u00a0\n\u00a0\n\u00a0\n\u00a0\n\u00a0\n\u00a0\n\u00a0\n\n\n\n\n/*<![CDATA[*/\nif (typeof DartIvwKategorie !== \"string\") window.DartIvwKategorie = \"boUndefined\";\n\nvar CP = \"//boss.berlinonline.de/cp.php?a=berlin&amp;r=\"+escape(document.referrer)+\"&amp;cat=\"+DartIvwKategorie+\"&amp;p=\"+escape(document.location)+\"&amp;d=\"+(Math.random()*100000);\ndocument.write(\"<img src=\\\"\"+CP+\"\\\" width=\\\"1\\\" height=\\\"1\\\" alt=\\\"\\\" id=\\\"cp_pixel\\\" style=\\\"position:absolute;width:1px;height:1px;\\\"/>\");\n/*]]>*/\n\n\n\n\nvar _paq = _paq || [];\n_paq.push([\"setDocumentTitle\", document.domain + \"/\" + document.title]);\n_paq.push([\"setCustomVariable\",1,\"Dart.active\",(typeof DartActive == \"boolean\" ? \"y\" : \"n\"),\"page\"]);\n_paq.push([\"trackPageView\"]);\n_paq.push([\"enableLinkTracking\"]);\n(function() {\nvar u=((\"https:\" == document.location.protocol) ? \"https\" : \"http\") + \"://piwik.berlinonline.de/\";\n_paq.push([\"setTrackerUrl\", u+\"piwik.php\"]);\n_paq.push([\"setSiteId\", \"1\"]);\nvar d=document, g=d.createElement(\"script\"), s=d.getElementsByTagName(\"script\")[0]; g.type=\"text/javascript\";\ng.defer=true; g.async=true; g.src=u+\"piwik.js\"; s.parentNode.insertBefore(g,s);\n})();\n\n\n\n\n\n\n\n\nvar iam_data = {\n\"mg\":\"yes\",\n\"cp\":DartIvwKategorie,\n\"st\":\"berlin\",\n\"sv\":(location.pathname==\"/\"?\"ke\":\"in\"),\n\"co\":location.hostname\n}\niom.c(iam_data,1);\n\n\n\n\n", "dsnr": "DS-0050-III"}}]}