{"type": "FeatureCollection", "features": [{"geometry": {"type": "Point", "coordinates": [13.226944, 52.561944]}, "type": "Feature", "properties": {"ausschuss": "", "bezirk": "Friedrichshain-Kreuzberg", "address": "", "title": "Drucksache DS/0705/IV\n", "url": null, "date": null, "typ": null, "text": "\n\n\n\n\nIch frage das Bezirksamt:\u00a0Wie ist der Sachstand zur Drucksache DS/0705/IV(Einmalige Leistungen und Umz\u00fcge im SGB II Und SGB XII rechtssicher handhaben)?\u00a0Sind die Formulare schon in der Beh\u00f6rde vorhanden?\u00a0Wann ist mit einer vollst\u00e4ndigen Umsetzung bei den Beh\u00f6rden zu rechnen?\u00a0\u00a0\u00a0\u00a0Bezirksamt Friedrichshain-Kreuzberg von Berlin\u00a0\u00a0\u00a0\u00a0\u00a0\u00a0\u00a0\u00a0\u00a0\u00a0\u00a0\u00a0\u00a0 14.08.2014Soziales, Besch\u00e4ftigung und B\u00fcrgerdienste\u00a0\u00a0\u00a0\u00a0\u00a0\u00a0\u00a0\u00a0\u00a0\u00a0\u00a0\u00a0\u00a0 -26014SozBeschB\u00fcD Dez\u00a0\u00a0Anbei \u00fcbersende ich die schriftliche Beantwortung der m\u00fcndlichen Anfrage.\u00a01. Wie ist der Sachstand zur Drucksache DS/0705/IV(Einmalige Leistungen und Umz\u00fcge im SGB II Und SGB XII rechtssicher handhaben)?2. Sind die Formulare schon in der Beh\u00f6rde vorhanden?\u00a03. Wann ist mit einer vollst\u00e4ndigen Umsetzung bei den Beh\u00f6rden zu rechnen?\u00a0Ich kann Ihnen zun\u00e4chst versichern, dass die Handhabung des SGB XII und des SGB II von den entsprechenden Dienststellen prinzipiell rechtssicher gehandhabt wird. Obwohl beide Verwaltungen mit der Umsetzung des Willens der DS 0705/IV beauftragt sind, ist diese noch nicht soweit gediehen, dass eine Vorlage zur Kenntnisnahme an die BVV erstellt werden konnte. \u00a0Das Anliegen der DS 0705/IV ist ein sehr umf\u00e4nglicher Auftrag, der es notwendig macht, zun\u00e4chst eine Sichtung der vorhandenen Formulare und Anschreiben an die B\u00fcrgerinnen und B\u00fcrger vorzunehmen und darauf folgend eine inhaltliche und kritische Auseinandersetzung mit diesen vorzunehmen. Beides beansprucht personelle Ressourcen und stellt dar\u00fcber hinaus eine zeitintensive Aufgabe dar, die neben der t\u00e4glichen operativen Leistungserbringung bew\u00e4ltigt werden muss. Aufgrund dringlicher Priorit\u00e4ten im regul\u00e4ren Dienstbetrieb sowie au\u00dfergew\u00f6hnlicher Problemlagen konnte die Erledigung dieser Drucksache daher zuletzt nicht mit der gebotenen Dringlichkeit erfolgen, was ich bedauere.\u00a0Zum jetzigen Zeitpunkt kann ich Ihnen auch noch nicht benennen, wann mit der vollst\u00e4ndigen Umsetzung des Anliegens der BVV zu rechnen ist.\u00a0Mit freundlichen Gr\u00fc\u00dfen\u00a0Knut Mildner- Spindler \u00a0\n\n\n/*<![CDATA[*/\nif (typeof DartIvwKategorie !== \"string\") window.DartIvwKategorie = \"boUndefined\";\n\nvar CP = \"//boss.berlinonline.de/cp.php?a=berlin&amp;r=\"+escape(document.referrer)+\"&amp;cat=\"+DartIvwKategorie+\"&amp;p=\"+escape(document.location)+\"&amp;d=\"+(Math.random()*100000);\ndocument.write(\"<img src=\\\"\"+CP+\"\\\" width=\\\"1\\\" height=\\\"1\\\" alt=\\\"\\\" id=\\\"cp_pixel\\\" style=\\\"position:absolute;width:1px;height:1px;\\\"/>\");\n/*]]>*/\n\n\n\n\nvar _paq = _paq || [];\n_paq.push([\"setDocumentTitle\", document.domain + \"/\" + document.title]);\n_paq.push([\"setCustomVariable\",1,\"Dart.active\",(typeof DartActive == \"boolean\" ? \"y\" : \"n\"),\"page\"]);\n_paq.push([\"trackPageView\"]);\n_paq.push([\"enableLinkTracking\"]);\n(function() {\nvar u=((\"https:\" == document.location.protocol) ? \"https\" : \"http\") + \"://piwik.berlinonline.de/\";\n_paq.push([\"setTrackerUrl\", u+\"piwik.php\"]);\n_paq.push([\"setSiteId\", \"1\"]);\nvar d=document, g=d.createElement(\"script\"), s=d.getElementsByTagName(\"script\")[0]; g.type=\"text/javascript\";\ng.defer=true; g.async=true; g.src=u+\"piwik.js\"; s.parentNode.insertBefore(g,s);\n})();\n\n\n\n\n\n\n\n\nvar iam_data = {\n\"mg\":\"yes\",\n\"cp\":DartIvwKategorie,\n\"st\":\"berlin\",\n\"sv\":(location.pathname==\"/\"?\"ke\":\"in\"),\n\"co\":location.hostname\n}\niom.c(iam_data,1);\n\n\n\n\n", "dsnr": "DS-1277-IV"}}]}