{"type": "FeatureCollection", "features": [{"type": "Feature", "properties": {"url": null, "title": "\u00c4nderungen der Gesch\u00e4ftsordnung\n", "bezirk": "Friedrichshain-Kreuzberg", "typ": null, "date": null, "dsnr": "DS-1647-02-IV", "ausschuss": "B\u00fcrgerbeteiligung", "address": "", "text": "\n\n\n\n\nDie Bezirksverordnetenversammlung m\u00f6ge beschlie\u00dfen:\u00a0Erg\u00e4nzung \u00a7 9 Absatz 1 Satz 3:Als anwesend gilt, wer mindestens f\u00fcr die H\u00e4lfte der Sitzungszeit anwesend war.\u00a0\u00a0Begr\u00fcndung:Die Zahlung der Sitzungsgelder im Rahmen einer Aufwandsentsch\u00e4digung sollte an einen entsprechenden Aufwand gekn\u00fcpft sein.\u00a0\u00a0B\u00fcTra 11.06.2015Der Antrag wird zur\u00fcckgezogen.\n\n\n/*<![CDATA[*/\nif (typeof DartIvwKategorie !== \"string\") window.DartIvwKategorie = \"boUndefined\";\n\nvar CP = \"//boss.berlinonline.de/cp.php?a=berlin&amp;r=\"+escape(document.referrer)+\"&amp;cat=\"+DartIvwKategorie+\"&amp;p=\"+escape(document.location)+\"&amp;d=\"+(Math.random()*100000);\ndocument.write(\"<img src=\\\"\"+CP+\"\\\" width=\\\"1\\\" height=\\\"1\\\" alt=\\\"\\\" id=\\\"cp_pixel\\\" style=\\\"position:absolute;width:1px;height:1px;\\\"/>\");\n/*]]>*/\n\n\n\n\nvar _paq = _paq || [];\n_paq.push([\"setDocumentTitle\", document.domain + \"/\" + document.title]);\n_paq.push([\"setCustomVariable\",1,\"Dart.active\",(typeof DartActive == \"boolean\" ? \"y\" : \"n\"),\"page\"]);\n_paq.push([\"trackPageView\"]);\n_paq.push([\"enableLinkTracking\"]);\n(function() {\nvar u=((\"https:\" == document.location.protocol) ? \"https\" : \"http\") + \"://piwik.berlinonline.de/\";\n_paq.push([\"setTrackerUrl\", u+\"piwik.php\"]);\n_paq.push([\"setSiteId\", \"1\"]);\nvar d=document, g=d.createElement(\"script\"), s=d.getElementsByTagName(\"script\")[0]; g.type=\"text/javascript\";\ng.defer=true; g.async=true; g.src=u+\"piwik.js\"; s.parentNode.insertBefore(g,s);\n})();\n\n\n\n\n\n\n\n\nvar iam_data = {\n\"mg\":\"yes\",\n\"cp\":DartIvwKategorie,\n\"st\":\"berlin\",\n\"sv\":(location.pathname==\"/\"?\"ke\":\"in\"),\n\"co\":location.hostname\n}\niom.c(iam_data,1);\n\n\n\n\n"}, "geometry": {"type": "Point", "coordinates": [13.226944, 52.561944]}}]}