{"type": "FeatureCollection", "features": [{"geometry": {"type": "Point", "coordinates": [13.226944, 52.561944]}, "type": "Feature", "properties": {"ausschuss": "Frauen; Kultur", "bezirk": "Friedrichshain-Kreuzberg", "address": ["Verk\u00e4ufer", ""], "title": "105 Jahre Frauentag am 8. M\u00e4rz 2016: Eine Ausstellung \u00fcber B\u00fcrger*innen des Bezirkes und ihre Berufe\n", "url": null, "date": null, "typ": null, "text": "\n\n\n\n\nDie Bezirksverordnetenversammlung m\u00f6ge beschlie\u00dfen:\u00a0Das Bezirksamt wird beauftragt, 105 Jahre Frauentag am 8. M\u00e4rz 2016 zum Anlass zu nehmen, eine Ausstellung zum Thema \"Friedrichshainer*innen und Kreuzberger*innen und ihre Berufe im Portrait\" zu konzipieren und diese 2016 an geeigneten Standorten im Bezirk zu zeigen. \u00a0Begr\u00fcndung:Mit dieser Ausstellung kann der Bezirk anl\u00e4sslich des Frauentages ein Zeichen der Anerkennung und W\u00fcrdigung von Frauen setzen und zugleich auf Forderungen aufmerksam machen, die auch mehr als 100 Jahre nach Einf\u00fchrung des Frauentages noch unerf\u00fcllt sind.\u00a0Von Gleichberechtigung ist vor allem in der Arbeitswelt noch wenig zu sp\u00fcren. Nach wie vor erhalten Frauen f\u00fcr gleiche Arbeit weniger Lohn als M\u00e4nner. Die Einfl\u00fcsse von spezifischen Belastungen der Frauen innerhalb der Familie und unzureichende gesellschaftliche Kapazit\u00e4ten bei der Kinderbetreuung oder Pflege Angeh\u00f6riger auf die Arbeitsmarktsituation sind unbestritten. Frauen sind oftmals in unterdurchschnittlich bezahlten Berufen t\u00e4tig, denen es allzu oft an gesellschaftlicher Wertsch\u00e4tzung fehlt. Pfleger*innen, Kita-Erzieher*innen, Reinigungskr\u00e4fte, Verk\u00e4ufer*innen leisten f\u00fcr unsere Gesellschaft viel, doch die w\u00fcnschenswerte Anerkennung ihrer Arbeit ist eine Seltenheit. \u00a0Die Ausstellung soll einen Beitrag dazu leisten, diesen Frauen ein Gesicht zu geben und ihre Verdienste zu w\u00fcrdigen sowie Forderungen nach Gleichberechtigung, wie gleichen Lohn f\u00fcr gleiche Arbeit, Nachdruck zu verleihen. Portr\u00e4tiert werden sollen Frauen, die im Bezirk leben oder arbeiten. Ihre verschiedenen Berufe, ihren Platz in der Arbeitswelt und in deren Hierarchien sowie ihre Biografien sollen mit diesen Portr\u00e4ts in einer Ausstellung sichtbar gemacht werden.\u00a0\u00a0BVV 25.03.2015Die Bezirksverordnetenversammlung beschlie\u00dft:\u00a0\u00dcberweisung: Ausschuss f\u00fcr Frauen, Gleichstellung und Queer,Ausschuss f\u00fcr Kultur und Bildung (federf\u00fchrend)\u00a0\u00a0KuBi 02.06.2015Die Bezirksverordnetenversammlung m\u00f6ge beschlie\u00dfen:\u00a0Das Bezirksamt wird beauftragt, 105 Jahre Frauentag am 8. M\u00e4rz 2016 zum Anlass zu nehmen, eine Ausstellung zum Thema \"Friedrichshainerinnen und Kreuzbergerinnen heute und ihre Berufe im Portrait\" zu konzipieren und diese in einem Zeitraum von 2016-2017 an geeigneten Standorten im Bezirk zu zeigen. \u00a0Diese soll besonders \u00fcber Drittmittel finanziert werden. \u00a0\u00a0BVV 24.06.2015Die Bezirksverordnetenversammlung beschlie\u00dft:\u00a0Das Bezirksamt wird beauftragt, 105 Jahre Frauentag am 8. M\u00e4rz 2016 zum Anlass zu nehmen, eine Ausstellung zum Thema \"Friedrichshainerinnen und Kreuzbergerinnen heute und ihre Berufe im Portrait\" zu konzipieren und diese in einem Zeitraum von 2016-2017 an geeigneten Standorten im Bezirk zu zeigen. \u00a0Diese soll besonders \u00fcber Drittmittel finanziert werden. \u00a0\n\n\n/*<![CDATA[*/\nif (typeof DartIvwKategorie !== \"string\") window.DartIvwKategorie = \"boUndefined\";\n\nvar CP = \"//boss.berlinonline.de/cp.php?a=berlin&amp;r=\"+escape(document.referrer)+\"&amp;cat=\"+DartIvwKategorie+\"&amp;p=\"+escape(document.location)+\"&amp;d=\"+(Math.random()*100000);\ndocument.write(\"<img src=\\\"\"+CP+\"\\\" width=\\\"1\\\" height=\\\"1\\\" alt=\\\"\\\" id=\\\"cp_pixel\\\" style=\\\"position:absolute;width:1px;height:1px;\\\"/>\");\n/*]]>*/\n\n\n\n\nvar _paq = _paq || [];\n_paq.push([\"setDocumentTitle\", document.domain + \"/\" + document.title]);\n_paq.push([\"setCustomVariable\",1,\"Dart.active\",(typeof DartActive == \"boolean\" ? \"y\" : \"n\"),\"page\"]);\n_paq.push([\"trackPageView\"]);\n_paq.push([\"enableLinkTracking\"]);\n(function() {\nvar u=((\"https:\" == document.location.protocol) ? \"https\" : \"http\") + \"://piwik.berlinonline.de/\";\n_paq.push([\"setTrackerUrl\", u+\"piwik.php\"]);\n_paq.push([\"setSiteId\", \"1\"]);\nvar d=document, g=d.createElement(\"script\"), s=d.getElementsByTagName(\"script\")[0]; g.type=\"text/javascript\";\ng.defer=true; g.async=true; g.src=u+\"piwik.js\"; s.parentNode.insertBefore(g,s);\n})();\n\n\n\n\n\n\n\n\nvar iam_data = {\n\"mg\":\"yes\",\n\"cp\":DartIvwKategorie,\n\"st\":\"berlin\",\n\"sv\":(location.pathname==\"/\"?\"ke\":\"in\"),\n\"co\":location.hostname\n}\niom.c(iam_data,1);\n\n\n\n\n", "dsnr": "DS-1602-IV"}}]}