{"type": "FeatureCollection", "features": [{"geometry": {"type": "Point", "coordinates": [13.226944, 52.561944]}, "type": "Feature", "properties": {"ausschuss": "", "bezirk": "Friedrichshain-Kreuzberg", "address": "", "title": "Investitionen in Regelungstechnik zur Senkung von Energiekosten\n", "url": null, "date": null, "typ": null, "text": "\n\n\n\n\nIch frage das Bezirksamt:\u00a01.\u00a0\u00a0\u00a0\u00a0\u00a0 Plant das Bezirksamt, einen Teil der den Bezirken zus\u00e4tzlich zur Verf\u00fcgung stehenden Mittel auch f\u00fcr Regelungstechnik einzusetzen, die zu Energieeinsparungen f\u00fchrt?\u00a02.\u00a0\u00a0\u00a0\u00a0\u00a0 Wenn ja, in welchem Umfang und in welchen Bereichen? / Wenn nein, warum nicht?\u00a03.\u00a0\u00a0\u00a0\u00a0\u00a0 In welcher Weise kann die bezirkliche Klimaschutzbeauftragte hier unterst\u00fctzend t\u00e4tig werden?\u00a0\u00a0\u00a0Bezirksamt Friedrichshain-Kreuzberg von Berlin\u00a0\u00a0\u00a0\u00a0\u00a0\u00a0\u00a0\u00a0\u00a0\u00a0\u00a0\u00a0\u00a0 \u00a0\u00a0\u00a0\u00a0\u00a0\u00a0\u00a0\u00a0\u00a0\u00a0\u00a0\u00a0\u00a0 \u00a0\u00a0\u00a0\u00a0\u00a0\u00a0\u00a0\u00a0\u00a0\u00a0\u00a0\u00a0\u00a0 \u00a0\u00a0\u00a0\u00a0\u00a0\u00a0\u00a0\u00a0\u00a0\u00a0\u00a0\u00a0\u00a0 \u00a0\u00a0\u00a0\u00a0\u00a0\u00a0\u00a0\u00a0\u00a0\u00a0\u00a0\u00a0\u00a0 25.02.2015Bezirksstadtr\u00e4tin f\u00fcr Finanzen, Facility Management, Weiterbildung und Kultur\u00a0Ihre o. g. Anfrage beantworte ich wie folgt:\u00a01. Plant das Bezirksamt, einen Teil der den Bezirken zus\u00e4tzlich zur Verf\u00fcgung ste\u00adhenden Mittel auch f\u00fcr die Regelungstechnik einzusetzen, die zu Energieeinspa\u00adrungen f\u00fchrt?\u00a0In Folge der Ausreichung der Mittel als konsumtive Sachausgaben ist dies nicht geplant.\u00a02. Wenn ja, in welchem Umfang und in welchen Bereichen? / Wenn nein, warum nicht?\u00a0Die dem Bezirk zus\u00e4tzlich zur Verf\u00fcgung gestellten Mittel sind in Ihrer Zweckbestimmung f\u00fcr Sanierungsma\u00dfnahmen zu verwenden. Das bedeutet, dass die konsumtiv bereitge\u00adstellten Mittel nicht f\u00fcr die Implementierung von Regeltechnik genutzt werden k\u00f6nnen, da dies der Zweckbestimmung gem. AV Nr. 1.1.3 zu \u00a724 \"...dies sind Ma\u00dfnahmen, die dazu dienen, bauliche Anlagen einschlie\u00dflich der Installationen, der zentralen Betriebstechnik, der betrieblichen Einbauten und der Au\u00dfenanlagen in gutem Zustand zu erhalten oder in guten Zustand zu setzen oder die Benutzbarkeit oder Leistungsf\u00e4higkeit dieser Anlagen auf Dauer zu sichern oder zu verbessern, ohne dass die bauliche Substanz wesentlich vermehrt oder ver\u00e4ndert wird.\" widerspr\u00e4che.\u00a03. In welcher Weise kann die bezirkliche Klimaschutzbeauftragte hier unterst\u00fct\u00adzend t\u00e4tig werden? \u00a0Da die den Bezirken zus\u00e4tzlich zur Verf\u00fcgung gestellten Mittel nicht f\u00fcr die Implementie\u00adrung von Regelungstechnik genutzt werden k\u00f6nnen, kann die Klimaschutzbeauftragte hier nicht effektiv unterst\u00fctzend t\u00e4tig werden.\u00a0Mit freundlichen Gr\u00fc\u00dfen\u00a0\u00a0\u00a0Jana BorkampBezirksstadtr\u00e4tin\u00a0\n\n\n/*<![CDATA[*/\nif (typeof DartIvwKategorie !== \"string\") window.DartIvwKategorie = \"boUndefined\";\n\nvar CP = \"//boss.berlinonline.de/cp.php?a=berlin&amp;r=\"+escape(document.referrer)+\"&amp;cat=\"+DartIvwKategorie+\"&amp;p=\"+escape(document.location)+\"&amp;d=\"+(Math.random()*100000);\ndocument.write(\"<img src=\\\"\"+CP+\"\\\" width=\\\"1\\\" height=\\\"1\\\" alt=\\\"\\\" id=\\\"cp_pixel\\\" style=\\\"position:absolute;width:1px;height:1px;\\\"/>\");\n/*]]>*/\n\n\n\n\nvar _paq = _paq || [];\n_paq.push([\"setDocumentTitle\", document.domain + \"/\" + document.title]);\n_paq.push([\"setCustomVariable\",1,\"Dart.active\",(typeof DartActive == \"boolean\" ? \"y\" : \"n\"),\"page\"]);\n_paq.push([\"trackPageView\"]);\n_paq.push([\"enableLinkTracking\"]);\n(function() {\nvar u=((\"https:\" == document.location.protocol) ? \"https\" : \"http\") + \"://piwik.berlinonline.de/\";\n_paq.push([\"setTrackerUrl\", u+\"piwik.php\"]);\n_paq.push([\"setSiteId\", \"1\"]);\nvar d=document, g=d.createElement(\"script\"), s=d.getElementsByTagName(\"script\")[0]; g.type=\"text/javascript\";\ng.defer=true; g.async=true; g.src=u+\"piwik.js\"; s.parentNode.insertBefore(g,s);\n})();\n\n\n\n\n\n\n\n\nvar iam_data = {\n\"mg\":\"yes\",\n\"cp\":DartIvwKategorie,\n\"st\":\"berlin\",\n\"sv\":(location.pathname==\"/\"?\"ke\":\"in\"),\n\"co\":location.hostname\n}\niom.c(iam_data,1);\n\n\n\n\n", "dsnr": "DS-1574-IV"}}]}