{"type": "FeatureCollection", "features": [{"geometry": {"type": "Point", "coordinates": [13.4531618, 52.5149611]}, "type": "Feature", "properties": {"ausschuss": "Stadtentwicklung; Wirtschaft", "bezirk": "Friedrichshain-Kreuzberg", "address": ["Warschauer Stra\u00dfe", "5"], "title": "Planungsziel f\u00fcr die Liegenschaft Frankfurter Tor 8A: Gewerbe\n", "url": null, "date": null, "typ": null, "text": "\n\n\n\n\nDie Bezirksverordnetenversammlung m\u00f6ge beschlie\u00dfen:\u00a0Das Bezirksamt soll sich daf\u00fcr einsetzen, dass die B\u00fcrogeb\u00e4ude Frankfurter Tor 8A ein Gewerbebau bleibt. Vor dem Hintergrund der bestehenden Nachfrage nach Gewerbefl\u00e4chen einerseits und der absehbaren Verdr\u00e4ngung von Gewerber\u00e4umen aus Wohngeb\u00e4uden im Zuge der mittelfristigen Umsetzung der Zweckentfremdungsverbotsverordnung, ist eine \u00c4nderung der Planungsziele des Bebauungsplans 2-41 geboten und die Umnutzung des B\u00fcrohauses zu einem Studierendenwohnheim nicht weiter zu verfolgen. Das Bezirksamt soll damit dazu beitragen, im Bezirk eine ausgewogene Mischung aus Wohnen und Arbeiten zu gew\u00e4hrleisten.\u00a0Begr\u00fcndung:\u00a0Der anhaltende Trend zum Wohnungsbau kann zur Schieflage auf dem lokalen Arbeitsmarkt f\u00fchren, wenn nicht gleichzeitig auch gewerbliche Fl\u00e4chen entstehen. Die Immobilie Frankfurter Tor 8A, Warschauer Stra\u00dfe 5-8 ist eine der wenigen Gewerbebauten im Bezirksteil. Zur Deckung der Nachfrage nach preiswertem Gewerberaum k\u00f6nnte hier ein Beitrag geleistet werden. Zudem gibt es auch Bildungstr\u00e4ger, die im Bezirksteil seit langem vergeblich R\u00e4ume suchen. Die Umnutzung des B\u00fcrohauses in ein Studierendenwohnheim w\u00fcrde eine der letzten Gewerberaumpotentiale im Kiez vernichten. Die mittelfristige Umsetzung der Zweckentfremdungsverbotsverordnung wird dazu f\u00fchren, dass eine nicht absehbare Zahl von B\u00fcros, Praxen etc. aus Wohngeb\u00e4uden ausziehen m\u00fcssen. Dies wird die Nachfrage nach ortsnahen und bezahlbaren Gewerber\u00e4umen verst\u00e4rken. Der Bezirk ist angehalten, auch diese absehbare Entwicklung rechzeitig zu ber\u00fccksichtigen und Gewerbestandorte zu sichern.\u00a0Die Piratenfraktion Friedrichshain-Kreuzberg entl\u00e4sst diesen Antragstext\u00a0 in die Gemeinfreiheit (Public Domain) als CC-0\u00a0 (http://creativecommons.org/publicdomain/zero/1.0/legalcode). Sie\u00a0 verzichtet weltweit auf alle urheberrechtlichen und verwandten\u00a0 Schutzrechte, soweit dies gesetzlich m\u00f6glich ist. Der Antragstext darf\u00a0 ohne weitere Erlaubnis kopiert, ver\u00e4ndert, verbreitet und aufgef\u00fchrt\u00a0 werden. Dies schliesst kommerzielle Zwecke explizit mit ein.\u00a0BVV 04.06.2014Die Bezirksverordnetenversammlung beschlie\u00dft:\u00a0\u00dcberweisung: Ausschuss f\u00fcr Wirtschaft und Ordnungsamt, Ausschuss f\u00fcr Stadtentwicklung, Soziale Stadt und Quartiersmanagement, Mieten (federf\u00fchrend).\u00a0\u00a0StadtQM 17.09.2014Die Bezirksverordnetenversammlung m\u00f6ge beschlie\u00dfen:\u00a0Der Antrag wird abgelehnt.\u00a0\u00a0BVV 24.09.2014Die Bezirksverordnetenversammlung beschlie\u00dft:\u00a0Der Antrag wird abgelehnt.\u00a0\n\n\n/*<![CDATA[*/\nif (typeof DartIvwKategorie !== \"string\") window.DartIvwKategorie = \"boUndefined\";\n\nvar CP = \"//boss.berlinonline.de/cp.php?a=berlin&amp;r=\"+escape(document.referrer)+\"&amp;cat=\"+DartIvwKategorie+\"&amp;p=\"+escape(document.location)+\"&amp;d=\"+(Math.random()*100000);\ndocument.write(\"<img src=\\\"\"+CP+\"\\\" width=\\\"1\\\" height=\\\"1\\\" alt=\\\"\\\" id=\\\"cp_pixel\\\" style=\\\"position:absolute;width:1px;height:1px;\\\"/>\");\n/*]]>*/\n\n\n\n\nvar _paq = _paq || [];\n_paq.push([\"setDocumentTitle\", document.domain + \"/\" + document.title]);\n_paq.push([\"setCustomVariable\",1,\"Dart.active\",(typeof DartActive == \"boolean\" ? \"y\" : \"n\"),\"page\"]);\n_paq.push([\"trackPageView\"]);\n_paq.push([\"enableLinkTracking\"]);\n(function() {\nvar u=((\"https:\" == document.location.protocol) ? \"https\" : \"http\") + \"://piwik.berlinonline.de/\";\n_paq.push([\"setTrackerUrl\", u+\"piwik.php\"]);\n_paq.push([\"setSiteId\", \"1\"]);\nvar d=document, g=d.createElement(\"script\"), s=d.getElementsByTagName(\"script\")[0]; g.type=\"text/javascript\";\ng.defer=true; g.async=true; g.src=u+\"piwik.js\"; s.parentNode.insertBefore(g,s);\n})();\n\n\n\n\n\n\n\n\nvar iam_data = {\n\"mg\":\"yes\",\n\"cp\":DartIvwKategorie,\n\"st\":\"berlin\",\n\"sv\":(location.pathname==\"/\"?\"ke\":\"in\"),\n\"co\":location.hostname\n}\niom.c(iam_data,1);\n\n\n\n\n", "dsnr": "DS-1200-IV"}}]}