{"type": "FeatureCollection", "features": [{"geometry": {"type": "Point", "coordinates": [13.226944, 52.561944]}, "type": "Feature", "properties": {"ausschuss": "Personal", "bezirk": "Friedrichshain-Kreuzberg", "address": "", "title": "Dezentrale Ausweisung und Aufl\u00f6sung der PMA sofort abschaffen!\n", "url": null, "date": null, "typ": null, "text": "\n\n\n\n\nDie Bezirksverordnetenversammlung m\u00f6ge beschlie\u00dfen:\u00a0Die Bezirksverordnetenversammlung fordert das Bezirksamt auf, von der \"dezentralen Ausweisung der Pauschalen Minderausgaben\" abzur\u00fccken. Insbesondere ist das Prinzip der \"dezentralen Aufl\u00f6sung\" sofort zu verwerfen.Im Textteil des Entwurfes des aktuellen Haushaltes hei\u00dft es unter Punkt 6, Unterpunkt 6.1, zweiter Absatz:\"Als Neuerung gegen\u00fcber Vorjahren hat sich das Bezirksamt dazu entschlossen, diese \u00dcberschreitungen als dezentrale Pauschale Minderausgaben auszuweisen und jeweils in der Haushaltswirtschaft dezentral aufzul\u00f6sen.\"Diese \"Neuerung\" ist wegen offensichtlicher Untauglichkeit und Gef\u00e4hrdung des Prinzips der Haushaltswahrheit und Haushaltsklarheit im laufenden Haushalt nicht mehr zur Anwendung zu bringen. Dar\u00fcber hinaus fordern wir das Bezirksamt auf, f\u00fcr zuk\u00fcnftige Haushalte keine derartigen Festlegungen mehr zu treffen.\u00a0Begr\u00fcndung:\u00a0Dieser Beschluss hat ein Konkurrenzdenken zwischen den einzelnen Verwaltungsbereichen und \u00c4mtern auf Bezirksebene zur Folge. Dar\u00fcber hinaus gef\u00e4hrdet es das Prinzip der Haushaltswahrheit und Haushaltsklarheit: Wenn das Schulamt und der zust\u00e4ndige Bezirksstadtrat Beckers im \"Ausschuss f\u00fcr Personal, Haushalt und Investitionen, Rechnungspr\u00fcfung\" erkl\u00e4ren, dass sie den Entwurf f\u00fcr den Bereich Schule nicht ausschlie\u00dflich auf Basis der Ans\u00e4tze und IST-Zahlen der vorangegangenen Jahre erstellen konnten, weil dies eine \u00dcberschreitung der dezentralen PMA zur Folge gehabt h\u00e4tte, sondern geringere Ans\u00e4tze angeben mussten, dann ist dies auf keinem Fall im Interesse der Bezirksverordneten - noch sonderlich transparent f\u00fcr die \u00d6ffentlichkeit.Dar\u00fcber hinaus beachtet das eingef\u00fchrte Prinzip nicht die unterschiedlichen strukturellen Rahmenbedingungen der Fachbereiche. Dass \"Schule\" einen hohen Immobilienbestand mit teilweise nicht seri\u00f6s kalkulierbaren Kosten aufweist, findet ebenso wenig Niederschlag, wie der grunds\u00e4tzliche Ansatz, dass Bereiche wie Soziales, Bildung und Jugend gesellschaftspolitisch notwendige Kernaufgaben sind, die nicht kaputt gespart werden sollten.\u00a0 \u00a0\u00a0BVV 25.02.2015Die Bezirksverordnetenversammlung beschlie\u00dft:\u00a0\u00dcberweisung: Ausschuss f\u00fcr Personal, Haushalt und Investitionen, Rechnungspr\u00fcfung.\u00a0\u00a0PHI 22.09.2015Die Bezirksverordnetenversammlung m\u00f6ge beschlie\u00dfen:\u00a0Der Antrag wird abgelehnt.\u00a0\u00a0BVV 23.09.2015Die Bezirksverordnetenversammlung beschlie\u00dft:\u00a0Der Antrag wird abgelehnt.\u00a0\n\n\n/*<![CDATA[*/\nif (typeof DartIvwKategorie !== \"string\") window.DartIvwKategorie = \"boUndefined\";\n\nvar CP = \"//boss.berlinonline.de/cp.php?a=berlin&amp;r=\"+escape(document.referrer)+\"&amp;cat=\"+DartIvwKategorie+\"&amp;p=\"+escape(document.location)+\"&amp;d=\"+(Math.random()*100000);\ndocument.write(\"<img src=\\\"\"+CP+\"\\\" width=\\\"1\\\" height=\\\"1\\\" alt=\\\"\\\" id=\\\"cp_pixel\\\" style=\\\"position:absolute;width:1px;height:1px;\\\"/>\");\n/*]]>*/\n\n\n\n\nvar _paq = _paq || [];\n_paq.push([\"setDocumentTitle\", document.domain + \"/\" + document.title]);\n_paq.push([\"setCustomVariable\",1,\"Dart.active\",(typeof DartActive == \"boolean\" ? \"y\" : \"n\"),\"page\"]);\n_paq.push([\"trackPageView\"]);\n_paq.push([\"enableLinkTracking\"]);\n(function() {\nvar u=((\"https:\" == document.location.protocol) ? \"https\" : \"http\") + \"://piwik.berlinonline.de/\";\n_paq.push([\"setTrackerUrl\", u+\"piwik.php\"]);\n_paq.push([\"setSiteId\", \"1\"]);\nvar d=document, g=d.createElement(\"script\"), s=d.getElementsByTagName(\"script\")[0]; g.type=\"text/javascript\";\ng.defer=true; g.async=true; g.src=u+\"piwik.js\"; s.parentNode.insertBefore(g,s);\n})();\n\n\n\n\n\n\n\n\nvar iam_data = {\n\"mg\":\"yes\",\n\"cp\":DartIvwKategorie,\n\"st\":\"berlin\",\n\"sv\":(location.pathname==\"/\"?\"ke\":\"in\"),\n\"co\":location.hostname\n}\niom.c(iam_data,1);\n\n\n\n\n", "dsnr": "DS-1543-IV"}}]}