{"type": "FeatureCollection", "features": [{"geometry": {"type": "Point", "coordinates": [13.226944, 52.561944]}, "type": "Feature", "properties": {"ausschuss": "B\u00fcrgerbeteiligung", "bezirk": "Friedrichshain-Kreuzberg", "address": "", "title": "Erweiterung der Gesch\u00e4ftsordnung unter VII \"B\u00fcrger*innenbeteiligung\"\n", "url": null, "date": null, "typ": null, "text": "\n\n\n\n\nDie Bezirksverordnetenversammlung m\u00f6ge beschlie\u00dfen:\u00a0Die Gesch\u00e4ftsordnung wird unter Punkt VII \"B\u00fcrger*innenbeteiligung\" um einen Paragraphen \"Worterteilung an andere Personen in \u00f6ffentlichen Sitzungen der BVV\" erweitert.\u00a0(1)\u00a0\u00a0 Andere Personen (Nicht-Mitglieder der BVV) k\u00f6nnen auf schriftlichen oder m\u00fcndlichen Antrag von der Vorsteher*in in die Redeliste zu einem Beratungsgegenstand aufgenommen werden. Der Antrag muss von mindestens sechs Verordneten unterst\u00fctzt werden. Die Worterteilung an andere Personen erfolgt, nachdem die momentane Redner*in mit ihrem Beitrag zum Beratungsgegenstand fertig ist.(2)\u00a0\u00a0 Die BVV kann mit den Stimmen der Mehrheit der anwesenden Mitglieder eine Redezeitbegrenzung festlegen.\u00a0Begr\u00fcndung: Die Abgrenzungsversuche zwischen BVV und Besucher*innen d\u00fcrfen nicht dazu f\u00fchren, dass es in Zukunft zu einer Abgeschottetheit in parlamentarischen Beratungen kommt. Die g\u00e4ngige Dialogform unserer BVV, dass spontane Redebeitr\u00e4ge der B\u00fcrger*innen in die Entscheidungsfindung der BVV Einzug erhalten, soll in der Gesch\u00e4ftsordnung fest verankert werden, wie es bereits im Bezirk Lichtenberg der Fall ist. Meinungs\u00e4u\u00dferungen der Besucher*innen finden so mehr Respekt, da ihnen ein gr\u00f6\u00dferes Gewicht beigemessen wird und werden im Gegenzug aufgrund der Aufmerksamkeit respektvoller formuliert werden. \u00a0B\u00fcTra 15.01.2015Die Bezirksverordnetenversammlung m\u00f6ge beschlie\u00dfen:\u00a0Der Antrag wird abgelehnt.\u00a0\u00a0BVV 28.01.2015Die Bezirksverordnetenversammlung beschlie\u00dft:\u00a0Der Antrag wird abgelehnt.\u00a0\n\n\n/*<![CDATA[*/\nif (typeof DartIvwKategorie !== \"string\") window.DartIvwKategorie = \"boUndefined\";\n\nvar CP = \"//boss.berlinonline.de/cp.php?a=berlin&amp;r=\"+escape(document.referrer)+\"&amp;cat=\"+DartIvwKategorie+\"&amp;p=\"+escape(document.location)+\"&amp;d=\"+(Math.random()*100000);\ndocument.write(\"<img src=\\\"\"+CP+\"\\\" width=\\\"1\\\" height=\\\"1\\\" alt=\\\"\\\" id=\\\"cp_pixel\\\" style=\\\"position:absolute;width:1px;height:1px;\\\"/>\");\n/*]]>*/\n\n\n\n\nvar _paq = _paq || [];\n_paq.push([\"setDocumentTitle\", document.domain + \"/\" + document.title]);\n_paq.push([\"setCustomVariable\",1,\"Dart.active\",(typeof DartActive == \"boolean\" ? \"y\" : \"n\"),\"page\"]);\n_paq.push([\"trackPageView\"]);\n_paq.push([\"enableLinkTracking\"]);\n(function() {\nvar u=((\"https:\" == document.location.protocol) ? \"https\" : \"http\") + \"://piwik.berlinonline.de/\";\n_paq.push([\"setTrackerUrl\", u+\"piwik.php\"]);\n_paq.push([\"setSiteId\", \"1\"]);\nvar d=document, g=d.createElement(\"script\"), s=d.getElementsByTagName(\"script\")[0]; g.type=\"text/javascript\";\ng.defer=true; g.async=true; g.src=u+\"piwik.js\"; s.parentNode.insertBefore(g,s);\n})();\n\n\n\n\n\n\n\n\nvar iam_data = {\n\"mg\":\"yes\",\n\"cp\":DartIvwKategorie,\n\"st\":\"berlin\",\n\"sv\":(location.pathname==\"/\"?\"ke\":\"in\"),\n\"co\":location.hostname\n}\niom.c(iam_data,1);\n\n\n\n\n", "dsnr": "DS-1446-IV"}}]}