{"type": "FeatureCollection", "features": [{"type": "Feature", "geometry": {"type": "Point", "coordinates": [13.226944, 52.561944]}, "properties": {"bezirk": "Friedrichshain-Kreuzberg", "title": "Vorhabenbezogener Bebauungsplan 2-44 VE f\u00fcr die Grundst\u00fccke Rigaer Stra\u00dfe 71-73A im Bezirk Friedrichshain-Kreuzberg, Ortsteil Friedrichshain hier: Aufstellungsbeschluss\n", "date": null, "ID": "FK_DS-1331-IV", "dsnr": "DS-1331-IV", "marker-color": "#0033dd"}}]}