{"type": "FeatureCollection", "features": [{"type": "Feature", "geometry": {"type": "Point", "coordinates": [13.226944, 52.561944]}, "properties": {"bezirk": "Friedrichshain-Kreuzberg", "marker-symbol": "information", "title": "Verletzung des Dienstgeheimnis im Bezirksamt Friedrichshain-Kreuzberg durch die Drucksache 1141/IV der BVV Friedrichshain-Kreuzberg (w\u00f6rtliches Zitat aus einem Beschluss des Bezirksamts vom 18.03.2014, der als \"Nur f\u00fcr den Dienstgebrauch\" gekennzeichnet war)! \n", "date": null, "ID": "FK_DS-1214-IV", "dsnr": "DS-1214-IV", "marker-color": "#000000"}}]}