{"features": [{"properties": {"ID": "FK_DS-1822-07-IV", "bezirk": "Friedrichshain-Kreuzberg", "title": "Entwurf des Bezirkshaushaltsplans f\u00fcr die Haushaltsjahre 2016 und 2017 Hier: Erhalt und Ausbau des B\u00fccherbus\n", "marker-color": "#ff0066", "date": null, "dsnr": "DS-1822-07-IV"}, "type": "FeatureCollection", "geometry": {"type": "Point", "coordinates": [13.226944, 52.561944]}}]}