{"type": "FeatureCollection", "features": [{"type": "Feature", "geometry": {"type": "Point", "coordinates": [13.226944, 52.561944]}, "properties": {"bezirk": "Friedrichshain-Kreuzberg", "title": "Anpassung des B-Plans V-83 Postareal an den st\u00e4dtebaulichen Vertrag\n", "date": null, "ID": "FK_DS-1383-IV", "dsnr": "DS-1383-IV", "marker-color": "#0033dd"}}]}