{"type": "FeatureCollection", "features": [{"type": "Feature", "geometry": {"type": "Point", "coordinates": [13.226944, 52.561944]}, "properties": {"bezirk": "Friedrichshain-Kreuzberg", "marker-symbol": "post", "title": "Mariannenplatzfest am l. Mai\n", "date": null, "ID": "FK_DS-0217-I", "dsnr": "DS-0217-I", "marker-color": "#0033dd"}}]}