{"type": "FeatureCollection", "features": [{"type": "Feature", "geometry": {"type": "Point", "coordinates": [13.226944, 52.561944]}, "properties": {"bezirk": "Friedrichshain-Kreuzberg", "title": "Entwurf des Bezirkshaushaltsplans f\u00fcr die Haushaltsjahre 2016 und 2017 Hier: Erhalt und Ausbau des B\u00fccherbus\n", "date": null, "ID": "FK_DS-1822-07-IV", "dsnr": "DS-1822-07-IV", "marker-color": "#ff0066"}}]}