{"type": "FeatureCollection", "features": [{"type": "Feature", "geometry": {"type": "Point", "coordinates": [13.226944, 52.561944]}, "properties": {"bezirk": "Friedrichshain-Kreuzberg", "marker-symbol": "post", "title": "Gemeinsame Resolution bez\u00fcglich der Unterst\u00fctzung einer gemeinsamen L\u00f6sung mit den Betroffenen zur Errichtung eines internationalen Fl\u00fcchtlingszentrums in der ehemaligen Gerhart-Hauptmann-Schule\n", "date": null, "ID": "FK_DS-1760-IV", "dsnr": "DS-1760-IV", "marker-color": "#ff8800"}}]}