{"type": "FeatureCollection", "features": [{"type": "Feature", "geometry": {"type": "Point", "coordinates": [13.226944, 52.561944]}, "properties": {"bezirk": "Friedrichshain-Kreuzberg", "title": "Ausreichende Mittel aus dem B\u00fcndnis f\u00fcr Wohnungsneubau f\u00fcr B\u00fcrgerbeteiligung bereitstellen\n", "date": null, "ID": "FK_DS-1523-IV", "dsnr": "DS-1523-IV", "marker-color": "#0033dd"}}]}