{"type": "FeatureCollection", "features": [{"type": "Feature", "geometry": {"type": "Point", "coordinates": [13.226944, 52.561944]}, "properties": {"bezirk": "Friedrichshain-Kreuzberg", "title": "Ma\u00dfnahmenplan Baerwaldbad\n", "date": null, "ID": "FK_DS-1737-IV", "dsnr": "DS-1737-IV", "marker-color": "#0033dd"}}]}