{"type": "FeatureCollection", "features": [{"type": "Feature", "geometry": {"type": "Point", "coordinates": [13.226944, 52.561944]}, "properties": {"bezirk": "Friedrichshain-Kreuzberg", "marker-symbol": "town-hall", "title": "Bildung des \u00c4ltestenrates\n", "date": null, "ID": "FK_DS-0002-I", "dsnr": "DS-0002-I", "marker-color": "#0033dd"}}]}