{"type": "FeatureCollection", "features": [{"type": "Feature", "geometry": {"type": "Point", "coordinates": [13.226944, 52.561944]}, "properties": {"bezirk": "Friedrichshain-Kreuzberg", "title": "Wahl von B\u00fcrgerdeputierten in die Aussch\u00fcsse gern. \u00a7 21 BezVG\n", "date": null, "ID": "FK_DS-0065-I", "dsnr": "DS-0065-I", "marker-color": "#0033dd"}}]}