{"type": "FeatureCollection", "features": [{"type": "Feature", "geometry": {"type": "Point", "coordinates": [13.226944, 52.561944]}, "properties": {"bezirk": "Friedrichshain-Kreuzberg", "marker-symbol": "information", "title": "Personalbedarf an Schulen\n", "date": null, "ID": "FK_DS-1557-IV", "dsnr": "DS-1557-IV", "marker-color": "#0033dd"}}]}