{"type": "FeatureCollection", "features": [{"type": "Feature", "geometry": {"type": "Point", "coordinates": [13.226944, 52.561944]}, "properties": {"bezirk": "Friedrichshain-Kreuzberg", "marker-symbol": "town-hall", "title": "Bericht \u00fcber soziale Wohnraumversorgung\n", "date": null, "ID": "FK_DS-1603-IV", "dsnr": "DS-1603-IV", "marker-color": "#ff0066"}}]}