{"type": "FeatureCollection", "features": [{"type": "Feature", "geometry": {"type": "Point", "coordinates": [13.226944, 52.561944]}, "properties": {"bezirk": "Friedrichshain-Kreuzberg", "marker-symbol": "information", "title": "Programm  Trans* in Arbeit\n", "date": null, "ID": "FK_DS-1273-IV", "dsnr": "DS-1273-IV", "marker-color": "#ff0000"}}]}